{"ref":"288551f0-3514-4bdc-b085-3468c002ef6f","syncData":{"version":1,"machineId":"b3e86fe4-53d7-4afa-a34c-f0985eaa54dd","content":"{\"storage\":{\"workbench.panel.markers.hidden\":{\"version\":1,\"value\":\"[{\\\"id\\\":\\\"workbench.panel.markers.view\\\",\\\"isHidden\\\":false}]\"},\"workbench.panel.output.hidden\":{\"version\":1,\"value\":\"[{\\\"id\\\":\\\"workbench.panel.output\\\",\\\"isHidden\\\":false}]\"},\"terminal.hidden\":{\"version\":1,\"value\":\"[{\\\"id\\\":\\\"terminal\\\",\\\"isHidden\\\":false}]\"},\"workbench.explorer.views.state.hidden\":{\"version\":1,\"value\":\"[{\\\"id\\\":\\\"outline\\\",\\\"isHidden\\\":false},{\\\"id\\\":\\\"timeline\\\",\\\"isHidden\\\":false},{\\\"id\\\":\\\"workbench.explorer.openEditorsView\\\",\\\"isHidden\\\":true},{\\\"id\\\":\\\"workbench.explorer.emptyView\\\",\\\"isHidden\\\":false},{\\\"id\\\":\\\"workbench.explorer.fileView\\\",\\\"isHidden\\\":false},{\\\"id\\\":\\\"npm\\\",\\\"isHidden\\\":true},{\\\"id\\\":\\\"javaProjectExplorer\\\",\\\"isHidden\\\":false},{\\\"id\\\":\\\"mavenProjects\\\",\\\"isHidden\\\":false},{\\\"id\\\":\\\"arduinoExampleExplorer\\\",\\\"isHidden\\\":false},{\\\"id\\\":\\\"xmlTreeView\\\",\\\"isHidden\\\":false},{\\\"id\\\":\\\"mysql\\\",\\\"isHidden\\\":false},{\\\"id\\\":\\\"dockerContainers\\\",\\\"isHidden\\\":false},{\\\"id\\\":\\\"dockerImages\\\",\\\"isHidden\\\":false},{\\\"id\\\":\\\"dockerRegistries\\\",\\\"isHidden\\\":false},{\\\"id\\\":\\\"dockerNetworks\\\",\\\"isHidden\\\":false},{\\\"id\\\":\\\"dockerVolumes\\\",\\\"isHidden\\\":false},{\\\"id\\\":\\\"vscode-docker.views.dockerContexts\\\",\\\"isHidden\\\":false},{\\\"id\\\":\\\"vscode-docker.views.help\\\",\\\"isHidden\\\":false},{\\\"id\\\":\\\"aws.codeWhisperer.referenceLog\\\",\\\"isHidden\\\":false},{\\\"id\\\":\\\"aws.amazonq.transformationHub\\\",\\\"isHidden\\\":false},{\\\"id\\\":\\\"aws.amazonq.transformationProposedChangesTree\\\",\\\"isHidden\\\":false},{\\\"id\\\":\\\"aws.amazonq.AmazonCommonAuth\\\",\\\"isHidden\\\":false},{\\\"id\\\":\\\"aws.AmazonQChatView\\\",\\\"isHidden\\\":false},{\\\"id\\\":\\\"aws.AmazonQNeverShowBadge\\\",\\\"isHidden\\\":false}]\"},\"workbench.scm.views.state.hidden\":{\"version\":1,\"value\":\"[{\\\"id\\\":\\\"workbench.scm.repositories\\\",\\\"isHidden\\\":true},{\\\"id\\\":\\\"workbench.scm\\\",\\\"isHidden\\\":false},{\\\"id\\\":\\\"gitlens.views.repositories\\\",\\\"isHidden\\\":true},{\\\"id\\\":\\\"gitlens.views.commits\\\",\\\"isHidden\\\":false},{\\\"id\\\":\\\"gitlens.views.branches\\\",\\\"isHidden\\\":false},{\\\"id\\\":\\\"gitlens.views.remotes\\\",\\\"isHidden\\\":false},{\\\"id\\\":\\\"gitlens.views.stashes\\\",\\\"isHidden\\\":false},{\\\"id\\\":\\\"gitlens.views.tags\\\",\\\"isHidden\\\":false},{\\\"id\\\":\\\"gitlens.views.worktrees\\\",\\\"isHidden\\\":false},{\\\"id\\\":\\\"gitlens.views.contributors\\\",\\\"isHidden\\\":false}]\"},\"workbench.view.search.state.hidden\":{\"version\":1,\"value\":\"[{\\\"id\\\":\\\"workbench.view.search\\\",\\\"isHidden\\\":false}]\"},\"workbench.activityBar.location\":{\"version\":1,\"value\":\"default\"},\"workbench.activity.pinnedViewlets2\":{\"version\":1,\"value\":\"[{\\\"id\\\":\\\"workbench.view.explorer\\\",\\\"pinned\\\":true,\\\"visible\\\":false,\\\"order\\\":0},{\\\"id\\\":\\\"workbench.view.search\\\",\\\"pinned\\\":true,\\\"visible\\\":false,\\\"order\\\":1},{\\\"id\\\":\\\"workbench.view.scm\\\",\\\"pinned\\\":true,\\\"visible\\\":false,\\\"order\\\":2},{\\\"id\\\":\\\"workbench.view.debug\\\",\\\"pinned\\\":true,\\\"visible\\\":false,\\\"order\\\":3},{\\\"id\\\":\\\"workbench.view.extensions\\\",\\\"pinned\\\":true,\\\"visible\\\":false,\\\"order\\\":4},{\\\"id\\\":\\\"workbench.view.remote\\\",\\\"pinned\\\":true,\\\"visible\\\":false,\\\"order\\\":4},{\\\"id\\\":\\\"workbench.view.extension.test\\\",\\\"pinned\\\":true,\\\"visible\\\":false,\\\"order\\\":6},{\\\"id\\\":\\\"workbench.view.extension.references-view\\\",\\\"pinned\\\":true,\\\"visible\\\":false,\\\"order\\\":7},{\\\"id\\\":\\\"workbench.view.extension.github-dbclient-history\\\",\\\"pinned\\\":true,\\\"visible\\\":false,\\\"order\\\":9},{\\\"id\\\":\\\"workbench.view.extension.dataworkspace\\\",\\\"pinned\\\":true,\\\"visible\\\":false,\\\"order\\\":14},{\\\"id\\\":\\\"workbench.view.extension.objectExplorer\\\",\\\"pinned\\\":true,\\\"visible\\\":false,\\\"order\\\":15},{\\\"id\\\":\\\"workbench.view.extension.cspell-explorer\\\",\\\"pinned\\\":true,\\\"visible\\\":false,\\\"order\\\":19},{\\\"id\\\":\\\"workbench.view.extension.gitlensPatch\\\",\\\"pinned\\\":true,\\\"visible\\\":false,\\\"order\\\":14},{\\\"id\\\":\\\"workbench.view.extension.cmake-view\\\",\\\"pinned\\\":true,\\\"visible\\\":false,\\\"order\\\":17},{\\\"id\\\":\\\"workbench.view.extension.sqltoolsActivityBarContainer\\\",\\\"pinned\\\":true,\\\"visible\\\":false,\\\"order\\\":15},{\\\"id\\\":\\\"workbench.view.extension.blackbox\\\",\\\"pinned\\\":true,\\\"visible\\\":false,\\\"order\\\":8},{\\\"id\\\":\\\"workbench.view.extension.thunder-client\\\",\\\"pinned\\\":true,\\\"visible\\\":false,\\\"order\\\":18},{\\\"id\\\":\\\"workbench.view.extension.console-ninja\\\",\\\"pinned\\\":true,\\\"visible\\\":false,\\\"order\\\":20},{\\\"id\\\":\\\"workbench.view.extension.github-cweijan-mysql\\\",\\\"pinned\\\":true,\\\"visible\\\":false,\\\"order\\\":8},{\\\"id\\\":\\\"workbench.view.extension.dockerView\\\",\\\"pinned\\\":true,\\\"visible\\\":false,\\\"order\\\":16},{\\\"id\\\":\\\"workbench.view.extension.github-actions\\\",\\\"pinned\\\":true,\\\"visible\\\":false,\\\"order\\\":15},{\\\"id\\\":\\\"workbench.view.extension.package-explorer\\\",\\\"pinned\\\":true,\\\"visible\\\":false,\\\"order\\\":11},{\\\"id\\\":\\\"workbench.panel.chatSidebar\\\",\\\"pinned\\\":true,\\\"visible\\\":false,\\\"order\\\":100},{\\\"id\\\":\\\"workbench.view.extension.github-cweijan-nosql\\\",\\\"pinned\\\":true,\\\"visible\\\":false,\\\"order\\\":10},{\\\"id\\\":\\\"workbench.view.extension.gitlensInspect\\\",\\\"pinned\\\":true,\\\"visible\\\":false,\\\"order\\\":13},{\\\"id\\\":\\\"workbench.view.extension.gitlens\\\",\\\"pinned\\\":true,\\\"visible\\\":false,\\\"order\\\":12},{\\\"id\\\":\\\"userDataProfiles\\\",\\\"pinned\\\":true,\\\"visible\\\":false},{\\\"id\\\":\\\"workbench.view.sync\\\",\\\"pinned\\\":true,\\\"visible\\\":false},{\\\"id\\\":\\\"workbench.view.editSessions\\\",\\\"pinned\\\":true,\\\"visible\\\":false}]\"},\"workbench.panel.pinnedPanels\":{\"version\":1,\"value\":\"[{\\\"id\\\":\\\"workbench.panel.markers\\\",\\\"pinned\\\":true,\\\"visible\\\":false,\\\"order\\\":0},{\\\"id\\\":\\\"workbench.panel.output\\\",\\\"pinned\\\":true,\\\"visible\\\":false,\\\"order\\\":1},{\\\"id\\\":\\\"workbench.panel.repl\\\",\\\"pinned\\\":true,\\\"visible\\\":false,\\\"order\\\":2},{\\\"id\\\":\\\"terminal\\\",\\\"pinned\\\":true,\\\"visible\\\":false,\\\"order\\\":3},{\\\"id\\\":\\\"workbench.panel.testResults\\\",\\\"pinned\\\":true,\\\"visible\\\":false,\\\"order\\\":3},{\\\"id\\\":\\\"~remote.forwardedPortsContainer\\\",\\\"pinned\\\":true,\\\"visible\\\":false,\\\"order\\\":5},{\\\"id\\\":\\\"workbench.view.extension.dbclient-search-result\\\",\\\"pinned\\\":true,\\\"visible\\\":false,\\\"order\\\":6},{\\\"id\\\":\\\"workbench.view.extension.gitlensPanel\\\",\\\"pinned\\\":true,\\\"visible\\\":false,\\\"order\\\":7},{\\\"id\\\":\\\"workbench.view.extension.vscode-serial-monitor-tools\\\",\\\"pinned\\\":true,\\\"visible\\\":false,\\\"order\\\":8},{\\\"id\\\":\\\"workbench.view.extension.sqltoolsPanelContainer\\\",\\\"pinned\\\":true,\\\"visible\\\":false,\\\"order\\\":8},{\\\"id\\\":\\\"workbench.view.extension.blackbox-terminal\\\",\\\"pinned\\\":true,\\\"visible\\\":false,\\\"order\\\":6},{\\\"id\\\":\\\"workbench.panel.comments\\\",\\\"pinned\\\":true,\\\"visible\\\":false,\\\"order\\\":10},{\\\"id\\\":\\\"refactorPreview\\\",\\\"pinned\\\":true,\\\"visible\\\":false}]\"},\"workbench.view.debug.state.hidden\":{\"version\":1,\"value\":\"[{\\\"id\\\":\\\"workbench.debug.welcome\\\",\\\"isHidden\\\":false},{\\\"id\\\":\\\"workbench.debug.variablesView\\\",\\\"isHidden\\\":false},{\\\"id\\\":\\\"workbench.debug.watchExpressionsView\\\",\\\"isHidden\\\":false},{\\\"id\\\":\\\"workbench.debug.callStackView\\\",\\\"isHidden\\\":false},{\\\"id\\\":\\\"workbench.debug.loadedScriptsView\\\",\\\"isHidden\\\":false},{\\\"id\\\":\\\"workbench.debug.breakPointsView\\\",\\\"isHidden\\\":false},{\\\"id\\\":\\\"jsBrowserBreakpoints\\\",\\\"isHidden\\\":false},{\\\"id\\\":\\\"jsExcludedCallers\\\",\\\"isHidden\\\":false},{\\\"id\\\":\\\"CppSshTargetsView\\\",\\\"isHidden\\\":false},{\\\"id\\\":\\\"jsDebugNetworkTree\\\",\\\"isHidden\\\":false}]\"},\"workbench.panel.repl.hidden\":{\"version\":1,\"value\":\"[{\\\"id\\\":\\\"workbench.panel.repl.view\\\",\\\"isHidden\\\":false}]\"},\"colorThemeData\":{\"version\":1,\"value\":\"{\\\"id\\\":\\\"vs-dark enkia-tokyo-night-themes-tokyo-night-color-theme-json\\\",\\\"label\\\":\\\"Tokyo Night\\\",\\\"settingsId\\\":\\\"Tokyo Night\\\",\\\"themeTokenColors\\\":[{\\\"settings\\\":{\\\"fontStyle\\\":\\\"italic\\\"},\\\"scope\\\":[\\\"comment\\\",\\\"meta.var.expr storage.type\\\",\\\"keyword.control.flow\\\",\\\"keyword.control.return\\\",\\\"meta.directive.vue punctuation.separator.key-value.html\\\",\\\"meta.directive.vue entity.other.attribute-name.html\\\",\\\"tag.decorator.js entity.name.tag.js\\\",\\\"tag.decorator.js punctuation.definition.tag.js\\\",\\\"storage.modifier\\\",\\\"string.quoted.docstring.multi\\\",\\\"string.quoted.docstring.multi.python punctuation.definition.string.begin\\\",\\\"string.quoted.docstring.multi.python punctuation.definition.string.end\\\",\\\"string.quoted.docstring.multi.python constant.character.escape\\\"]},{\\\"settings\\\":{\\\"fontStyle\\\":\\\"\\\"},\\\"scope\\\":[\\\"keyword.control.flow.block-scalar.literal\\\",\\\"keyword.control.flow.python\\\"]},{\\\"settings\\\":{\\\"foreground\\\":\\\"#51597d\\\"},\\\"scope\\\":[\\\"comment\\\",\\\"comment.block.documentation\\\",\\\"punctuation.definition.comment\\\",\\\"comment.block.documentation punctuation\\\",\\\"string.quoted.docstring.multi\\\",\\\"string.quoted.docstring.multi.python punctuation.definition.string.begin\\\",\\\"string.quoted.docstring.multi.python punctuation.definition.string.end\\\",\\\"string.quoted.docstring.multi.python constant.character.escape\\\"]},{\\\"settings\\\":{\\\"foreground\\\":\\\"#5a638c\\\"},\\\"scope\\\":[\\\"keyword.operator.assignment.jsdoc\\\",\\\"comment.block.documentation variable\\\",\\\"comment.block.documentation storage\\\",\\\"comment.block.documentation keyword\\\",\\\"comment.block.documentation support\\\",\\\"comment.block.documentation markup\\\",\\\"comment.block.documentation markup.inline.raw.string.markdown\\\",\\\"meta.other.type.phpdoc.php keyword.other.type.php\\\",\\\"meta.other.type.phpdoc.php support.other.namespace.php\\\",\\\"meta.other.type.phpdoc.php punctuation.separator.inheritance.php\\\",\\\"meta.other.type.phpdoc.php support.class\\\",\\\"keyword.other.phpdoc.php\\\",\\\"log.date\\\"]},{\\\"settings\\\":{\\\"foreground\\\":\\\"#646e9c\\\"},\\\"scope\\\":[\\\"meta.other.type.phpdoc.php support.class\\\",\\\"comment.block.documentation storage.type\\\",\\\"comment.block.documentation punctuation.definition.block.tag\\\",\\\"comment.block.documentation entity.name.type.instance\\\"]},{\\\"settings\\\":{\\\"foreground\\\":\\\"#ff9e64\\\"},\\\"scope\\\":[\\\"variable.other.constant\\\",\\\"punctuation.definition.constant\\\",\\\"constant.language\\\",\\\"constant.numeric\\\",\\\"support.constant\\\",\\\"constant.other.caps\\\"]},{\\\"settings\\\":{\\\"fontStyle\\\":\\\"\\\",\\\"foreground\\\":\\\"#9ece6a\\\"},\\\"scope\\\":[\\\"string\\\",\\\"constant.other.symbol\\\",\\\"constant.other.key\\\",\\\"meta.attribute-selector\\\",\\\"string constant.character\\\"]},{\\\"settings\\\":{\\\"foreground\\\":\\\"#9aa5ce\\\"},\\\"scope\\\":[\\\"constant.other.color\\\",\\\"constant.other.color.rgb-value.hex punctuation.definition.constant\\\"]},{\\\"settings\\\":{\\\"foreground\\\":\\\"#ff5370\\\"},\\\"scope\\\":[\\\"invalid\\\",\\\"invalid.illegal\\\"]},{\\\"settings\\\":{\\\"foreground\\\":\\\"#bb9af7\\\"},\\\"scope\\\":\\\"invalid.deprecated\\\"},{\\\"settings\\\":{\\\"foreground\\\":\\\"#bb9af7\\\"},\\\"scope\\\":\\\"storage.type\\\"},{\\\"settings\\\":{\\\"foreground\\\":\\\"#9d7cd8\\\"},\\\"scope\\\":[\\\"meta.var.expr storage.type\\\",\\\"storage.modifier\\\"]},{\\\"settings\\\":{\\\"foreground\\\":\\\"#7dcfff\\\"},\\\"scope\\\":[\\\"punctuation.definition.template-expression\\\",\\\"punctuation.section.embedded\\\",\\\"meta.embedded.line.tag.smarty\\\",\\\"support.constant.handlebars\\\",\\\"punctuation.section.tag.twig\\\"]},{\\\"settings\\\":{\\\"foreground\\\":\\\"#0db9d7\\\"},\\\"scope\\\":[\\\"keyword.control.smarty\\\",\\\"keyword.control.twig\\\",\\\"support.constant.handlebars keyword.control\\\",\\\"keyword.operator.comparison.twig\\\",\\\"keyword.blade\\\",\\\"entity.name.function.blade\\\"]},{\\\"settings\\\":{\\\"foreground\\\":\\\"#f7768e\\\",\\\"fontStyle\\\":\\\"bold\\\"},\\\"scope\\\":[\\\"keyword.operator.spread\\\",\\\"keyword.operator.rest\\\"]},{\\\"settings\\\":{\\\"foreground\\\":\\\"#89ddff\\\"},\\\"scope\\\":[\\\"keyword.operator\\\",\\\"keyword.control.as\\\",\\\"keyword.other\\\",\\\"keyword.operator.bitwise.shift\\\",\\\"punctuation\\\",\\\"expression.embbeded.vue punctuation.definition.tag\\\",\\\"text.html.twig meta.tag.inline.any.html\\\",\\\"meta.tag.template.value.twig meta.function.arguments.twig\\\",\\\"meta.directive.vue punctuation.separator.key-value.html\\\",\\\"punctuation.definition.constant.markdown\\\",\\\"punctuation.definition.string\\\",\\\"punctuation.support.type.property-name\\\",\\\"text.html.vue-html meta.tag\\\",\\\"meta.attribute.directive\\\",\\\"punctuation.definition.keyword\\\",\\\"punctuation.terminator.rule\\\",\\\"punctuation.definition.entity\\\",\\\"punctuation.separator.inheritance.php\\\",\\\"keyword.other.template\\\",\\\"keyword.other.substitution\\\",\\\"entity.name.operator\\\",\\\"meta.property-list punctuation.separator.key-value\\\",\\\"meta.at-rule.mixin punctuation.separator.key-value\\\",\\\"meta.at-rule.function variable.parameter.url\\\"]},{\\\"settings\\\":{\\\"foreground\\\":\\\"#7dcfff\\\"},\\\"scope\\\":[\\\"keyword.control.module.js\\\",\\\"keyword.control.import\\\",\\\"keyword.control.export\\\",\\\"keyword.control.from\\\",\\\"keyword.control.default\\\",\\\"meta.import keyword.other\\\"]},{\\\"settings\\\":{\\\"foreground\\\":\\\"#bb9af7\\\"},\\\"scope\\\":[\\\"keyword\\\",\\\"keyword.control\\\",\\\"keyword.other.important\\\"]},{\\\"settings\\\":{\\\"foreground\\\":\\\"#7dcfff\\\"},\\\"scope\\\":\\\"keyword.other.DML\\\"},{\\\"settings\\\":{\\\"foreground\\\":\\\"#bb9af7\\\"},\\\"scope\\\":[\\\"keyword.operator.logical\\\",\\\"storage.type.function\\\",\\\"keyword.operator.bitwise\\\",\\\"keyword.operator.ternary\\\",\\\"keyword.operator.comparison\\\",\\\"keyword.operator.relational\\\",\\\"keyword.operator.or.regexp\\\"]},{\\\"settings\\\":{\\\"foreground\\\":\\\"#f7768e\\\"},\\\"scope\\\":\\\"entity.name.tag\\\"},{\\\"settings\\\":{\\\"foreground\\\":\\\"#de5971\\\"},\\\"scope\\\":[\\\"entity.name.tag support.class.component\\\",\\\"meta.tag.custom entity.name.tag\\\",\\\"meta.tag.other.unrecognized.html.derivative entity.name.tag\\\",\\\"meta.tag\\\"]},{\\\"settings\\\":{\\\"foreground\\\":\\\"#ba3c97\\\"},\\\"scope\\\":\\\"punctuation.definition.tag\\\"},{\\\"settings\\\":{\\\"foreground\\\":\\\"#e0af68\\\"},\\\"scope\\\":[\\\"constant.other.php\\\",\\\"variable.other.global.safer\\\",\\\"variable.other.global.safer punctuation.definition.variable\\\",\\\"variable.other.global\\\",\\\"variable.other.global punctuation.definition.variable\\\",\\\"constant.other\\\"]},{\\\"settings\\\":{\\\"foreground\\\":\\\"#c0caf5\\\"},\\\"scope\\\":[\\\"variable\\\",\\\"support.variable\\\",\\\"string constant.other.placeholder\\\",\\\"variable.parameter.handlebars\\\",\\\"variable.other.object\\\",\\\"meta.fstring\\\",\\\"meta.function-call meta.function-call.arguments\\\"]},{\\\"settings\\\":{\\\"foreground\\\":\\\"#7dcfff\\\"},\\\"scope\\\":\\\"meta.array.literal variable\\\"},{\\\"settings\\\":{\\\"foreground\\\":\\\"#73daca\\\"},\\\"scope\\\":[\\\"meta.object-literal.key\\\",\\\"entity.name.type.hcl\\\",\\\"string.alias.graphql\\\",\\\"string.unquoted.graphql\\\",\\\"string.unquoted.alias.graphql\\\",\\\"meta.group.braces.curly constant.other.object.key.js string.unquoted.label.js\\\",\\\"meta.field.declaration.ts variable.object.property\\\",\\\"meta.block entity.name.label\\\"]},{\\\"settings\\\":{\\\"foreground\\\":\\\"#7dcfff\\\"},\\\"scope\\\":[\\\"variable.other.property\\\",\\\"support.variable.property\\\",\\\"support.variable.property.dom\\\",\\\"meta.function-call variable.other.object.property\\\"]},{\\\"settings\\\":{\\\"foreground\\\":\\\"#c0caf5\\\"},\\\"scope\\\":\\\"variable.other.object.property\\\"},{\\\"settings\\\":{\\\"foreground\\\":\\\"#41a6b5\\\"},\\\"scope\\\":\\\"meta.objectliteral meta.object.member meta.objectliteral meta.object.member meta.objectliteral meta.object.member meta.object-literal.key\\\"},{\\\"settings\\\":{\\\"foreground\\\":\\\"#f7768e\\\"},\\\"scope\\\":\\\"source.cpp meta.block variable.other\\\"},{\\\"settings\\\":{\\\"foreground\\\":\\\"#f7768e\\\"},\\\"scope\\\":\\\"support.other.variable\\\"},{\\\"settings\\\":{\\\"foreground\\\":\\\"#7aa2f7\\\"},\\\"scope\\\":[\\\"meta.class-method.js entity.name.function.js\\\",\\\"entity.name.method.js\\\",\\\"variable.function.constructor\\\",\\\"keyword.other.special-method\\\",\\\"storage.type.cs\\\"]},{\\\"settings\\\":{\\\"foreground\\\":\\\"#7aa2f7\\\"},\\\"scope\\\":[\\\"entity.name.function\\\",\\\"variable.other.enummember\\\",\\\"meta.function-call\\\",\\\"meta.function-call entity.name.function\\\",\\\"variable.function\\\",\\\"meta.definition.method entity.name.function\\\",\\\"meta.object-literal entity.name.function\\\"]},{\\\"settings\\\":{\\\"foreground\\\":\\\"#e0af68\\\"},\\\"scope\\\":[\\\"variable.parameter.function.language.special\\\",\\\"variable.parameter\\\",\\\"meta.function.parameters punctuation.definition.variable\\\",\\\"meta.function.parameter variable\\\"]},{\\\"settings\\\":{\\\"foreground\\\":\\\"#bb9af7\\\"},\\\"scope\\\":[\\\"keyword.other.type.php\\\",\\\"storage.type.php\\\",\\\"constant.character\\\",\\\"constant.escape\\\",\\\"keyword.other.unit\\\"]},{\\\"settings\\\":{\\\"foreground\\\":\\\"#bb9af7\\\"},\\\"scope\\\":[\\\"meta.definition.variable variable.other.constant\\\",\\\"meta.definition.variable variable.other.readwrite\\\",\\\"variable.declaration.hcl variable.other.readwrite.hcl\\\",\\\"meta.mapping.key.hcl variable.other.readwrite.hcl\\\",\\\"variable.other.declaration\\\"]},{\\\"settings\\\":{\\\"fontStyle\\\":\\\"\\\",\\\"foreground\\\":\\\"#bb9af7\\\"},\\\"scope\\\":\\\"entity.other.inherited-class\\\"},{\\\"settings\\\":{\\\"foreground\\\":\\\"#0db9d7\\\"},\\\"scope\\\":[\\\"support.class\\\",\\\"support.type\\\",\\\"variable.other.readwrite.alias\\\",\\\"support.orther.namespace.use.php\\\",\\\"meta.use.php\\\",\\\"support.other.namespace.php\\\",\\\"support.type.sys-types\\\",\\\"support.variable.dom\\\",\\\"support.constant.math\\\",\\\"support.type.object.module\\\",\\\"support.constant.json\\\",\\\"entity.name.namespace\\\",\\\"meta.import.qualifier\\\",\\\"variable.other.constant.object\\\"]},{\\\"settings\\\":{\\\"foreground\\\":\\\"#c0caf5\\\"},\\\"scope\\\":\\\"entity.name\\\"},{\\\"settings\\\":{\\\"foreground\\\":\\\"#0db9d7\\\"},\\\"scope\\\":\\\"support.function\\\"},{\\\"settings\\\":{\\\"foreground\\\":\\\"#7aa2f7\\\"},\\\"scope\\\":[\\\"source.css support.type.property-name\\\",\\\"source.sass support.type.property-name\\\",\\\"source.scss support.type.property-name\\\",\\\"source.less support.type.property-name\\\",\\\"source.stylus support.type.property-name\\\",\\\"source.postcss support.type.property-name\\\",\\\"support.type.property-name.css\\\",\\\"support.type.vendored.property-name\\\",\\\"support.type.map.key\\\"]},{\\\"settings\\\":{\\\"foreground\\\":\\\"#9ece6a\\\"},\\\"scope\\\":[\\\"support.constant.font-name\\\",\\\"meta.definition.variable\\\"]},{\\\"settings\\\":{\\\"foreground\\\":\\\"#9ece6a\\\"},\\\"scope\\\":[\\\"entity.other.attribute-name.class\\\",\\\"meta.at-rule.mixin.scss entity.name.function.scss\\\"]},{\\\"settings\\\":{\\\"foreground\\\":\\\"#fc7b7b\\\"},\\\"scope\\\":\\\"entity.other.attribute-name.id\\\"},{\\\"settings\\\":{\\\"foreground\\\":\\\"#0db9d7\\\"},\\\"scope\\\":\\\"entity.name.tag.css\\\"},{\\\"settings\\\":{\\\"foreground\\\":\\\"#e0af68\\\"},\\\"scope\\\":[\\\"entity.other.attribute-name.pseudo-class punctuation.definition.entity\\\",\\\"entity.other.attribute-name.pseudo-element punctuation.definition.entity\\\",\\\"entity.other.attribute-name.class punctuation.definition.entity\\\",\\\"entity.name.tag.reference\\\"]},{\\\"settings\\\":{\\\"foreground\\\":\\\"#9abdf5\\\"},\\\"scope\\\":\\\"meta.property-list\\\"},{\\\"settings\\\":{\\\"foreground\\\":\\\"#ff9e64\\\"},\\\"scope\\\":[\\\"meta.property-list meta.at-rule.if\\\",\\\"meta.at-rule.return variable.parameter.url\\\",\\\"meta.property-list meta.at-rule.else\\\"]},{\\\"settings\\\":{\\\"foreground\\\":\\\"#73daca\\\"},\\\"scope\\\":[\\\"entity.other.attribute-name.parent-selector-suffix punctuation.definition.entity.css\\\"]},{\\\"settings\\\":{\\\"foreground\\\":\\\"#9abdf5\\\"},\\\"scope\\\":\\\"meta.property-list meta.property-list\\\"},{\\\"settings\\\":{\\\"foreground\\\":\\\"#bb9af7\\\"},\\\"scope\\\":[\\\"meta.at-rule.mixin keyword.control.at-rule.mixin\\\",\\\"meta.at-rule.include entity.name.function.scss\\\",\\\"meta.at-rule.include keyword.control.at-rule.include\\\"]},{\\\"settings\\\":{\\\"foreground\\\":\\\"#9d7cd8\\\"},\\\"scope\\\":[\\\"keyword.control.at-rule.include punctuation.definition.keyword\\\",\\\"keyword.control.at-rule.mixin punctuation.definition.keyword\\\",\\\"meta.at-rule.include keyword.control.at-rule.include\\\",\\\"keyword.control.at-rule.extend punctuation.definition.keyword\\\",\\\"meta.at-rule.extend keyword.control.at-rule.extend\\\",\\\"entity.other.attribute-name.placeholder.css punctuation.definition.entity.css\\\",\\\"meta.at-rule.media keyword.control.at-rule.media\\\",\\\"meta.at-rule.mixin keyword.control.at-rule.mixin\\\",\\\"meta.at-rule.function keyword.control.at-rule.function\\\",\\\"keyword.control punctuation.definition.keyword\\\"]},{\\\"settings\\\":{\\\"foreground\\\":\\\"#c0caf5\\\"},\\\"scope\\\":\\\"meta.property-list meta.at-rule.include\\\"},{\\\"settings\\\":{\\\"foreground\\\":\\\"#ff9e64\\\"},\\\"scope\\\":\\\"support.constant.property-value\\\"},{\\\"settings\\\":{\\\"foreground\\\":\\\"#c0caf5\\\"},\\\"scope\\\":[\\\"entity.name.module.js\\\",\\\"variable.import.parameter.js\\\",\\\"variable.other.class.js\\\"]},{\\\"settings\\\":{\\\"foreground\\\":\\\"#f7768e\\\"},\\\"scope\\\":\\\"variable.language\\\"},{\\\"settings\\\":{\\\"foreground\\\":\\\"#c0caf5\\\"},\\\"scope\\\":\\\"variable.other punctuation.definition.variable\\\"},{\\\"settings\\\":{\\\"foreground\\\":\\\"#f7768e\\\"},\\\"scope\\\":[\\\"source.js constant.other.object.key.js string.unquoted.label.js\\\",\\\"variable.language.this punctuation.definition.variable\\\",\\\"keyword.other.this\\\"]},{\\\"settings\\\":{\\\"foreground\\\":\\\"#bb9af7\\\"},\\\"scope\\\":[\\\"entity.other.attribute-name\\\",\\\"text.html.basic entity.other.attribute-name.html\\\",\\\"text.html.basic entity.other.attribute-name\\\"]},{\\\"settings\\\":{\\\"foreground\\\":\\\"#0DB9D7\\\"},\\\"scope\\\":\\\"text.html constant.character.entity\\\"},{\\\"settings\\\":{\\\"foreground\\\":\\\"#bb9af7\\\"},\\\"scope\\\":[\\\"entity.other.attribute-name.id.html\\\",\\\"meta.directive.vue entity.other.attribute-name.html\\\"]},{\\\"settings\\\":{\\\"foreground\\\":\\\"#7aa2f7\\\"},\\\"scope\\\":\\\"source.sass keyword.control\\\"},{\\\"settings\\\":{\\\"foreground\\\":\\\"#bb9af7\\\"},\\\"scope\\\":[\\\"entity.other.attribute-name.pseudo-class\\\",\\\"entity.other.attribute-name.pseudo-element\\\",\\\"entity.other.attribute-name.placeholder\\\",\\\"meta.property-list meta.property-value\\\"]},{\\\"settings\\\":{\\\"foreground\\\":\\\"#449dab\\\"},\\\"scope\\\":\\\"markup.inserted\\\"},{\\\"settings\\\":{\\\"foreground\\\":\\\"#914c54\\\"},\\\"scope\\\":\\\"markup.deleted\\\"},{\\\"settings\\\":{\\\"foreground\\\":\\\"#6183bb\\\"},\\\"scope\\\":\\\"markup.changed\\\"},{\\\"settings\\\":{\\\"foreground\\\":\\\"#b4f9f8\\\"},\\\"scope\\\":\\\"string.regexp\\\"},{\\\"settings\\\":{\\\"foreground\\\":\\\"#f7768e\\\"},\\\"scope\\\":\\\"punctuation.definition.group\\\"},{\\\"settings\\\":{\\\"foreground\\\":\\\"#bb9af7\\\"},\\\"scope\\\":[\\\"constant.other.character-class.regexp\\\"]},{\\\"settings\\\":{\\\"foreground\\\":\\\"#e0af68\\\"},\\\"scope\\\":[\\\"constant.other.character-class.set.regexp\\\",\\\"punctuation.definition.character-class.regexp\\\"]},{\\\"settings\\\":{\\\"foreground\\\":\\\"#89ddff\\\"},\\\"scope\\\":\\\"keyword.operator.quantifier.regexp\\\"},{\\\"settings\\\":{\\\"foreground\\\":\\\"#c0caf5\\\"},\\\"scope\\\":\\\"constant.character.escape.backslash\\\"},{\\\"settings\\\":{\\\"foreground\\\":\\\"#89ddff\\\"},\\\"scope\\\":\\\"constant.character.escape\\\"},{\\\"settings\\\":{\\\"foreground\\\":\\\"#7aa2f7\\\"},\\\"scope\\\":[\\\"tag.decorator.js entity.name.tag.js\\\",\\\"tag.decorator.js punctuation.definition.tag.js\\\"]},{\\\"settings\\\":{\\\"foreground\\\":\\\"#f7768e\\\"},\\\"scope\\\":\\\"keyword.other.unit\\\"},{\\\"settings\\\":{\\\"foreground\\\":\\\"#7aa2f7\\\"},\\\"scope\\\":[\\\"source.json meta.structure.dictionary.json support.type.property-name.json\\\"]},{\\\"settings\\\":{\\\"foreground\\\":\\\"#0db9d7\\\"},\\\"scope\\\":[\\\"source.json meta.structure.dictionary.json meta.structure.dictionary.value.json meta.structure.dictionary.json support.type.property-name.json\\\"]},{\\\"settings\\\":{\\\"foreground\\\":\\\"#7dcfff\\\"},\\\"scope\\\":[\\\"source.json meta.structure.dictionary.json meta.structure.dictionary.value.json meta.structure.dictionary.json meta.structure.dictionary.value.json meta.structure.dictionary.json support.type.property-name.json\\\"]},{\\\"settings\\\":{\\\"foreground\\\":\\\"#bb9af7\\\"},\\\"scope\\\":[\\\"source.json meta.structure.dictionary.json meta.structure.dictionary.value.json meta.structure.dictionary.json meta.structure.dictionary.value.json meta.structure.dictionary.json meta.structure.dictionary.value.json meta.structure.dictionary.json support.type.property-name.json\\\"]},{\\\"settings\\\":{\\\"foreground\\\":\\\"#e0af68\\\"},\\\"scope\\\":[\\\"source.json meta.structure.dictionary.json meta.structure.dictionary.value.json meta.structure.dictionary.json meta.structure.dictionary.value.json meta.structure.dictionary.json meta.structure.dictionary.value.json meta.structure.dictionary.json meta.structure.dictionary.value.json meta.structure.dictionary.json support.type.property-name.json\\\"]},{\\\"settings\\\":{\\\"foreground\\\":\\\"#0db9d7\\\"},\\\"scope\\\":[\\\"source.json meta.structure.dictionary.json meta.structure.dictionary.value.json meta.structure.dictionary.json meta.structure.dictionary.value.json meta.structure.dictionary.json meta.structure.dictionary.value.json meta.structure.dictionary.json meta.structure.dictionary.value.json meta.structure.dictionary.json meta.structure.dictionary.value.json meta.structure.dictionary.json support.type.property-name.json\\\"]},{\\\"settings\\\":{\\\"foreground\\\":\\\"#73daca\\\"},\\\"scope\\\":[\\\"source.json meta.structure.dictionary.json meta.structure.dictionary.value.json meta.structure.dictionary.json meta.structure.dictionary.value.json meta.structure.dictionary.json meta.structure.dictionary.value.json meta.structure.dictionary.json meta.structure.dictionary.value.json meta.structure.dictionary.json meta.structure.dictionary.value.json meta.structure.dictionary.json meta.structure.dictionary.value.json meta.structure.dictionary.json support.type.property-name.json\\\"]},{\\\"settings\\\":{\\\"foreground\\\":\\\"#f7768e\\\"},\\\"scope\\\":[\\\"source.json meta.structure.dictionary.json meta.structure.dictionary.value.json meta.structure.dictionary.json meta.structure.dictionary.value.json meta.structure.dictionary.json meta.structure.dictionary.value.json meta.structure.dictionary.json meta.structure.dictionary.value.json meta.structure.dictionary.json meta.structure.dictionary.value.json meta.structure.dictionary.json meta.structure.dictionary.value.json meta.structure.dictionary.json meta.structure.dictionary.value.json meta.structure.dictionary.json support.type.property-name.json\\\"]},{\\\"settings\\\":{\\\"foreground\\\":\\\"#9ece6a\\\"},\\\"scope\\\":[\\\"source.json meta.structure.dictionary.json meta.structure.dictionary.value.json meta.structure.dictionary.json meta.structure.dictionary.value.json meta.structure.dictionary.json meta.structure.dictionary.value.json meta.structure.dictionary.json meta.structure.dictionary.value.json meta.structure.dictionary.json meta.structure.dictionary.value.json meta.structure.dictionary.json meta.structure.dictionary.value.json meta.structure.dictionary.json meta.structure.dictionary.value.json meta.structure.dictionary.json meta.structure.dictionary.value.json meta.structure.dictionary.json support.type.property-name.json\\\"]},{\\\"settings\\\":{\\\"foreground\\\":\\\"#9abdf5\\\"},\\\"scope\\\":\\\"punctuation.definition.list_item.markdown\\\"},{\\\"settings\\\":{\\\"foreground\\\":\\\"#9abdf5\\\"},\\\"scope\\\":[\\\"meta.block\\\",\\\"meta.brace\\\",\\\"punctuation.definition.block\\\",\\\"punctuation.definition.use\\\",\\\"punctuation.definition.class\\\",\\\"punctuation.definition.begin.bracket\\\",\\\"punctuation.definition.end.bracket\\\",\\\"punctuation.definition.switch-expression.begin.bracket\\\",\\\"punctuation.definition.switch-expression.end.bracket\\\",\\\"punctuation.definition.section.switch-block.begin.bracket\\\",\\\"punctuation.definition.section.switch-block.end.bracket\\\",\\\"punctuation.definition.group.shell\\\",\\\"punctuation.definition.parameters\\\",\\\"punctuation.definition.arguments\\\",\\\"punctuation.definition.dictionary\\\",\\\"punctuation.definition.array\\\",\\\"punctuation.section\\\"]},{\\\"settings\\\":{\\\"foreground\\\":\\\"#c0caf5\\\"},\\\"scope\\\":[\\\"meta.embedded.block\\\"]},{\\\"settings\\\":{\\\"foreground\\\":\\\"#9aa5ce\\\"},\\\"scope\\\":[\\\"meta.tag JSXNested\\\",\\\"meta.jsx.children\\\",\\\"text.html\\\",\\\"text.log\\\"]},{\\\"settings\\\":{\\\"foreground\\\":\\\"#bb9af7\\\"},\\\"scope\\\":\\\"text.html.markdown markup.inline.raw.markdown\\\"},{\\\"settings\\\":{\\\"foreground\\\":\\\"#4E5579\\\"},\\\"scope\\\":\\\"text.html.markdown markup.inline.raw.markdown punctuation.definition.raw.markdown\\\"},{\\\"settings\\\":{\\\"fontStyle\\\":\\\"bold\\\",\\\"foreground\\\":\\\"#89ddff\\\"},\\\"scope\\\":[\\\"heading.1.markdown entity.name\\\",\\\"heading.1.markdown punctuation.definition.heading.markdown\\\"]},{\\\"settings\\\":{\\\"fontStyle\\\":\\\"bold\\\",\\\"foreground\\\":\\\"#61bdf2\\\"},\\\"scope\\\":[\\\"heading.2.markdown entity.name\\\",\\\"heading.2.markdown punctuation.definition.heading.markdown\\\"]},{\\\"settings\\\":{\\\"fontStyle\\\":\\\"bold\\\",\\\"foreground\\\":\\\"#7aa2f7\\\"},\\\"scope\\\":[\\\"heading.3.markdown entity.name\\\",\\\"heading.3.markdown punctuation.definition.heading.markdown\\\"]},{\\\"settings\\\":{\\\"fontStyle\\\":\\\"bold\\\",\\\"foreground\\\":\\\"#6d91de\\\"},\\\"scope\\\":[\\\"heading.4.markdown entity.name\\\",\\\"heading.4.markdown punctuation.definition.heading.markdown\\\"]},{\\\"settings\\\":{\\\"fontStyle\\\":\\\"bold\\\",\\\"foreground\\\":\\\"#9aa5ce\\\"},\\\"scope\\\":[\\\"heading.5.markdown entity.name\\\",\\\"heading.5.markdown punctuation.definition.heading.markdown\\\"]},{\\\"settings\\\":{\\\"fontStyle\\\":\\\"bold\\\",\\\"foreground\\\":\\\"#747ca1\\\"},\\\"scope\\\":[\\\"heading.6.markdown entity.name\\\",\\\"heading.6.markdown punctuation.definition.heading.markdown\\\"]},{\\\"settings\\\":{\\\"fontStyle\\\":\\\"italic\\\",\\\"foreground\\\":\\\"#c0caf5\\\"},\\\"scope\\\":[\\\"markup.italic\\\",\\\"markup.italic punctuation\\\"]},{\\\"settings\\\":{\\\"fontStyle\\\":\\\"bold\\\",\\\"foreground\\\":\\\"#c0caf5\\\"},\\\"scope\\\":[\\\"markup.bold\\\",\\\"markup.bold punctuation\\\"]},{\\\"settings\\\":{\\\"fontStyle\\\":\\\"bold italic\\\",\\\"foreground\\\":\\\"#c0caf5\\\"},\\\"scope\\\":[\\\"markup.bold markup.italic\\\",\\\"markup.bold markup.italic punctuation\\\"]},{\\\"settings\\\":{\\\"fontStyle\\\":\\\"underline\\\"},\\\"scope\\\":[\\\"markup.underline\\\",\\\"markup.underline punctuation\\\"]},{\\\"settings\\\":{\\\"foreground\\\":\\\"#4e5579\\\"},\\\"scope\\\":\\\"markup.quote punctuation.definition.blockquote.markdown\\\"},{\\\"settings\\\":{\\\"fontStyle\\\":\\\"italic\\\"},\\\"scope\\\":\\\"markup.quote\\\"},{\\\"settings\\\":{\\\"foreground\\\":\\\"#73daca\\\"},\\\"scope\\\":[\\\"string.other.link\\\",\\\"markup.underline.link\\\",\\\"constant.other.reference.link.markdown\\\",\\\"string.other.link.description.title.markdown\\\"]},{\\\"settings\\\":{\\\"foreground\\\":\\\"#89ddff\\\"},\\\"scope\\\":[\\\"markup.fenced_code.block.markdown\\\",\\\"markup.inline.raw.string.markdown\\\",\\\"variable.language.fenced.markdown\\\"]},{\\\"settings\\\":{\\\"fontStyle\\\":\\\"bold\\\",\\\"foreground\\\":\\\"#51597d\\\"},\\\"scope\\\":\\\"meta.separator\\\"},{\\\"settings\\\":{\\\"foreground\\\":\\\"#c0cefc\\\"},\\\"scope\\\":\\\"markup.table\\\"},{\\\"settings\\\":{\\\"foreground\\\":\\\"#0db9d7\\\"},\\\"scope\\\":\\\"token.info-token\\\"},{\\\"settings\\\":{\\\"foreground\\\":\\\"#ffdb69\\\"},\\\"scope\\\":\\\"token.warn-token\\\"},{\\\"settings\\\":{\\\"foreground\\\":\\\"#db4b4b\\\"},\\\"scope\\\":\\\"token.error-token\\\"},{\\\"settings\\\":{\\\"foreground\\\":\\\"#b267e6\\\"},\\\"scope\\\":\\\"token.debug-token\\\"},{\\\"settings\\\":{\\\"foreground\\\":\\\"#f7768e\\\"},\\\"scope\\\":\\\"entity.tag.apacheconf\\\"},{\\\"settings\\\":{\\\"foreground\\\":\\\"#73daca\\\"},\\\"scope\\\":[\\\"meta.preprocessor\\\"]},{\\\"settings\\\":{\\\"foreground\\\":\\\"#7aa2f7\\\"},\\\"scope\\\":\\\"source.env\\\"}],\\\"semanticTokenRules\\\":[{\\\"_selector\\\":\\\"parameter.declaration\\\",\\\"_style\\\":{\\\"_foreground\\\":\\\"#e0af68\\\",\\\"_bold\\\":null,\\\"_underline\\\":null,\\\"_italic\\\":null,\\\"_strikethrough\\\":null}},{\\\"_selector\\\":\\\"parameter\\\",\\\"_style\\\":{\\\"_foreground\\\":\\\"#d9d4cd\\\",\\\"_bold\\\":null,\\\"_underline\\\":null,\\\"_italic\\\":null,\\\"_strikethrough\\\":null}},{\\\"_selector\\\":\\\"property.declaration\\\",\\\"_style\\\":{\\\"_foreground\\\":\\\"#73daca\\\",\\\"_bold\\\":null,\\\"_underline\\\":null,\\\"_italic\\\":null,\\\"_strikethrough\\\":null}},{\\\"_selector\\\":\\\"property.defaultLibrary\\\",\\\"_style\\\":{\\\"_foreground\\\":\\\"#2ac3de\\\",\\\"_bold\\\":null,\\\"_underline\\\":null,\\\"_italic\\\":null,\\\"_strikethrough\\\":null}},{\\\"_selector\\\":\\\"*.defaultLibrary\\\",\\\"_style\\\":{\\\"_foreground\\\":\\\"#2ac3de\\\",\\\"_bold\\\":null,\\\"_underline\\\":null,\\\"_italic\\\":null,\\\"_strikethrough\\\":null}},{\\\"_selector\\\":\\\"variable.defaultLibrary\\\",\\\"_style\\\":{\\\"_foreground\\\":\\\"#2ac3de\\\",\\\"_bold\\\":null,\\\"_underline\\\":null,\\\"_italic\\\":null,\\\"_strikethrough\\\":null}},{\\\"_selector\\\":\\\"variable.declaration\\\",\\\"_style\\\":{\\\"_foreground\\\":\\\"#bb9af7\\\",\\\"_bold\\\":null,\\\"_underline\\\":null,\\\"_italic\\\":null,\\\"_strikethrough\\\":null}},{\\\"_selector\\\":\\\"variable\\\",\\\"_style\\\":{\\\"_foreground\\\":\\\"#c0caf5\\\",\\\"_bold\\\":null,\\\"_underline\\\":null,\\\"_italic\\\":null,\\\"_strikethrough\\\":null}}],\\\"extensionData\\\":{\\\"_extensionId\\\":\\\"enkia.tokyo-night\\\",\\\"_extensionIsBuiltin\\\":false,\\\"_extensionName\\\":\\\"tokyo-night\\\",\\\"_extensionPublisher\\\":\\\"enkia\\\"},\\\"colorMap\\\":{\\\"foreground\\\":\\\"#787c99\\\",\\\"descriptionForeground\\\":\\\"#515670\\\",\\\"focusBorder\\\":\\\"#545c7e33\\\",\\\"errorForeground\\\":\\\"#515670\\\",\\\"widget.shadow\\\":\\\"#ffffff00\\\",\\\"scrollbar.shadow\\\":\\\"#00000033\\\",\\\"badge.background\\\":\\\"#7e83b230\\\",\\\"badge.foreground\\\":\\\"#acb0d0\\\",\\\"icon.foreground\\\":\\\"#787c99\\\",\\\"settings.headerForeground\\\":\\\"#6183bb\\\",\\\"window.activeBorder\\\":\\\"#0d0f17\\\",\\\"window.inactiveBorder\\\":\\\"#0d0f17\\\",\\\"sash.hoverBorder\\\":\\\"#29355a\\\",\\\"toolbar.activeBackground\\\":\\\"#202330\\\",\\\"toolbar.hoverBackground\\\":\\\"#202330\\\",\\\"extensionButton.prominentBackground\\\":\\\"#3d59a1dd\\\",\\\"extensionButton.prominentHoverBackground\\\":\\\"#3d59a1aa\\\",\\\"extensionButton.prominentForeground\\\":\\\"#ffffff\\\",\\\"extensionBadge.remoteBackground\\\":\\\"#3d59a1\\\",\\\"extensionBadge.remoteForeground\\\":\\\"#ffffff\\\",\\\"button.background\\\":\\\"#3d59a1dd\\\",\\\"button.hoverBackground\\\":\\\"#3d59a1aa\\\",\\\"button.secondaryBackground\\\":\\\"#3b3e52\\\",\\\"button.foreground\\\":\\\"#ffffff\\\",\\\"progressBar.background\\\":\\\"#3d59a1\\\",\\\"input.background\\\":\\\"#14141b\\\",\\\"input.foreground\\\":\\\"#a9b1d6\\\",\\\"input.border\\\":\\\"#0f0f14\\\",\\\"input.placeholderForeground\\\":\\\"#787c998a\\\",\\\"inputOption.activeForeground\\\":\\\"#c0caf5\\\",\\\"inputOption.activeBackground\\\":\\\"#3d59a144\\\",\\\"inputValidation.infoForeground\\\":\\\"#bbc2e0\\\",\\\"inputValidation.infoBackground\\\":\\\"#3d59a15c\\\",\\\"inputValidation.infoBorder\\\":\\\"#3d59a1\\\",\\\"inputValidation.warningForeground\\\":\\\"#000000\\\",\\\"inputValidation.warningBackground\\\":\\\"#c2985b\\\",\\\"inputValidation.warningBorder\\\":\\\"#e0af68\\\",\\\"inputValidation.errorForeground\\\":\\\"#bbc2e0\\\",\\\"inputValidation.errorBackground\\\":\\\"#85353e\\\",\\\"inputValidation.errorBorder\\\":\\\"#963c47\\\",\\\"dropdown.foreground\\\":\\\"#787c99\\\",\\\"dropdown.background\\\":\\\"#14141b\\\",\\\"dropdown.listBackground\\\":\\\"#14141b\\\",\\\"activityBar.background\\\":\\\"#16161e\\\",\\\"activityBar.foreground\\\":\\\"#787c99\\\",\\\"activityBar.inactiveForeground\\\":\\\"#3b3e52\\\",\\\"activityBar.border\\\":\\\"#16161e\\\",\\\"activityBarBadge.background\\\":\\\"#3d59a1\\\",\\\"activityBarBadge.foreground\\\":\\\"#ffffff\\\",\\\"activityBarTop.foreground\\\":\\\"#787c99\\\",\\\"activityBarTop.inactiveForeground\\\":\\\"#3b3e52\\\",\\\"tree.indentGuidesStroke\\\":\\\"#2b2b3b\\\",\\\"sideBar.foreground\\\":\\\"#787c99\\\",\\\"sideBar.background\\\":\\\"#16161e\\\",\\\"sideBar.border\\\":\\\"#101014\\\",\\\"sideBarTitle.foreground\\\":\\\"#787c99\\\",\\\"sideBarSectionHeader.background\\\":\\\"#16161e\\\",\\\"sideBarSectionHeader.foreground\\\":\\\"#a9b1d6\\\",\\\"sideBarSectionHeader.border\\\":\\\"#101014\\\",\\\"sideBar.dropBackground\\\":\\\"#1e202e\\\",\\\"list.dropBackground\\\":\\\"#1e202e\\\",\\\"list.deemphasizedForeground\\\":\\\"#787c99\\\",\\\"list.activeSelectionBackground\\\":\\\"#202330\\\",\\\"list.activeSelectionForeground\\\":\\\"#a9b1d6\\\",\\\"list.inactiveSelectionBackground\\\":\\\"#1c1d29\\\",\\\"list.inactiveSelectionForeground\\\":\\\"#a9b1d6\\\",\\\"list.focusBackground\\\":\\\"#1c1d29\\\",\\\"list.focusForeground\\\":\\\"#a9b1d6\\\",\\\"list.hoverBackground\\\":\\\"#13131a\\\",\\\"list.hoverForeground\\\":\\\"#a9b1d6\\\",\\\"list.highlightForeground\\\":\\\"#668ac4\\\",\\\"list.invalidItemForeground\\\":\\\"#c97018\\\",\\\"list.errorForeground\\\":\\\"#bb616b\\\",\\\"list.warningForeground\\\":\\\"#c49a5a\\\",\\\"listFilterWidget.background\\\":\\\"#101014\\\",\\\"listFilterWidget.outline\\\":\\\"#3d59a1\\\",\\\"listFilterWidget.noMatchesOutline\\\":\\\"#a6333f\\\",\\\"pickerGroup.foreground\\\":\\\"#a9b1d6\\\",\\\"pickerGroup.border\\\":\\\"#101014\\\",\\\"scrollbarSlider.background\\\":\\\"#868bc415\\\",\\\"scrollbarSlider.hoverBackground\\\":\\\"#868bc410\\\",\\\"scrollbarSlider.activeBackground\\\":\\\"#868bc422\\\",\\\"editorBracketHighlight.foreground1\\\":\\\"#698cd6\\\",\\\"editorBracketHighlight.foreground2\\\":\\\"#68b3de\\\",\\\"editorBracketHighlight.foreground3\\\":\\\"#9a7ecc\\\",\\\"editorBracketHighlight.foreground4\\\":\\\"#25aac2\\\",\\\"editorBracketHighlight.foreground5\\\":\\\"#80a856\\\",\\\"editorBracketHighlight.foreground6\\\":\\\"#c49a5a\\\",\\\"editorBracketHighlight.unexpectedBracket.foreground\\\":\\\"#db4b4b\\\",\\\"editorBracketPairGuide.activeBackground1\\\":\\\"#698cd6\\\",\\\"editorBracketPairGuide.activeBackground2\\\":\\\"#68b3de\\\",\\\"editorBracketPairGuide.activeBackground3\\\":\\\"#9a7ecc\\\",\\\"editorBracketPairGuide.activeBackground4\\\":\\\"#25aac2\\\",\\\"editorBracketPairGuide.activeBackground5\\\":\\\"#80a856\\\",\\\"editorBracketPairGuide.activeBackground6\\\":\\\"#c49a5a\\\",\\\"selection.background\\\":\\\"#515c7e40\\\",\\\"editor.background\\\":\\\"#1a1b26\\\",\\\"editor.foreground\\\":\\\"#a9b1d6\\\",\\\"editor.foldBackground\\\":\\\"#1111174a\\\",\\\"editorLink.activeForeground\\\":\\\"#acb0d0\\\",\\\"editor.selectionBackground\\\":\\\"#515c7e4d\\\",\\\"editor.inactiveSelectionBackground\\\":\\\"#515c7e25\\\",\\\"editor.findMatchBackground\\\":\\\"#3d59a166\\\",\\\"editor.findMatchBorder\\\":\\\"#e0af68\\\",\\\"editor.findMatchHighlightBackground\\\":\\\"#3d59a166\\\",\\\"editor.findRangeHighlightBackground\\\":\\\"#515c7e33\\\",\\\"editor.rangeHighlightBackground\\\":\\\"#515c7e20\\\",\\\"editor.wordHighlightBackground\\\":\\\"#515c7e44\\\",\\\"editor.wordHighlightStrongBackground\\\":\\\"#515c7e55\\\",\\\"editor.selectionHighlightBackground\\\":\\\"#515c7e44\\\",\\\"editorCursor.foreground\\\":\\\"#c0caf5\\\",\\\"editorIndentGuide.background1\\\":\\\"#232433\\\",\\\"editorIndentGuide.activeBackground1\\\":\\\"#363b54\\\",\\\"editorLineNumber.foreground\\\":\\\"#363b54\\\",\\\"editorLineNumber.activeForeground\\\":\\\"#737aa2\\\",\\\"editor.lineHighlightBackground\\\":\\\"#1e202e\\\",\\\"editorWhitespace.foreground\\\":\\\"#363b54\\\",\\\"editorMarkerNavigation.background\\\":\\\"#16161e\\\",\\\"editorHoverWidget.background\\\":\\\"#16161e\\\",\\\"editorHoverWidget.border\\\":\\\"#101014\\\",\\\"editorBracketMatch.background\\\":\\\"#16161e\\\",\\\"editorBracketMatch.border\\\":\\\"#42465d\\\",\\\"editorOverviewRuler.border\\\":\\\"#101014\\\",\\\"editorOverviewRuler.errorForeground\\\":\\\"#db4b4b\\\",\\\"editorOverviewRuler.warningForeground\\\":\\\"#e0af68\\\",\\\"editorOverviewRuler.infoForeground\\\":\\\"#1abc9c\\\",\\\"editorOverviewRuler.bracketMatchForeground\\\":\\\"#101014\\\",\\\"editorOverviewRuler.findMatchForeground\\\":\\\"#a9b1d644\\\",\\\"editorOverviewRuler.rangeHighlightForeground\\\":\\\"#a9b1d644\\\",\\\"editorOverviewRuler.selectionHighlightForeground\\\":\\\"#a9b1d622\\\",\\\"editorOverviewRuler.wordHighlightForeground\\\":\\\"#bb9af755\\\",\\\"editorOverviewRuler.wordHighlightStrongForeground\\\":\\\"#bb9af766\\\",\\\"editorOverviewRuler.modifiedForeground\\\":\\\"#394b70\\\",\\\"editorOverviewRuler.addedForeground\\\":\\\"#164846\\\",\\\"editorOverviewRuler.deletedForeground\\\":\\\"#703438\\\",\\\"editorRuler.foreground\\\":\\\"#101014\\\",\\\"editorError.foreground\\\":\\\"#db4b4b\\\",\\\"editorWarning.foreground\\\":\\\"#e0af68\\\",\\\"editorInfo.foreground\\\":\\\"#0da0ba\\\",\\\"editorHint.foreground\\\":\\\"#0da0ba\\\",\\\"editorGutter.modifiedBackground\\\":\\\"#394b70\\\",\\\"editorGutter.addedBackground\\\":\\\"#164846\\\",\\\"editorGutter.deletedBackground\\\":\\\"#823c41\\\",\\\"editorGhostText.foreground\\\":\\\"#646e9c\\\",\\\"minimapGutter.modifiedBackground\\\":\\\"#425882\\\",\\\"minimapGutter.addedBackground\\\":\\\"#1c5957\\\",\\\"minimapGutter.deletedBackground\\\":\\\"#944449\\\",\\\"editorGroup.border\\\":\\\"#101014\\\",\\\"editorGroup.dropBackground\\\":\\\"#1e202e\\\",\\\"editorGroupHeader.tabsBorder\\\":\\\"#101014\\\",\\\"editorGroupHeader.tabsBackground\\\":\\\"#16161e\\\",\\\"editorGroupHeader.noTabsBackground\\\":\\\"#16161e\\\",\\\"editorGroupHeader.border\\\":\\\"#101014\\\",\\\"editorPane.background\\\":\\\"#16161e\\\",\\\"editorWidget.foreground\\\":\\\"#787c99\\\",\\\"editorWidget.background\\\":\\\"#16161e\\\",\\\"editorWidget.resizeBorder\\\":\\\"#545c7e33\\\",\\\"editorSuggestWidget.background\\\":\\\"#16161e\\\",\\\"editorSuggestWidget.border\\\":\\\"#101014\\\",\\\"editorSuggestWidget.selectedBackground\\\":\\\"#20222c\\\",\\\"editorSuggestWidget.highlightForeground\\\":\\\"#6183bb\\\",\\\"editorCodeLens.foreground\\\":\\\"#51597d\\\",\\\"editorLightBulb.foreground\\\":\\\"#e0af68\\\",\\\"editorLightBulbAutoFix.foreground\\\":\\\"#e0af68\\\",\\\"peekView.border\\\":\\\"#101014\\\",\\\"peekViewEditor.background\\\":\\\"#16161e\\\",\\\"peekViewEditor.matchHighlightBackground\\\":\\\"#3d59a166\\\",\\\"peekViewTitle.background\\\":\\\"#101014\\\",\\\"peekViewTitleLabel.foreground\\\":\\\"#a9b1d6\\\",\\\"peekViewTitleDescription.foreground\\\":\\\"#787c99\\\",\\\"peekViewResult.background\\\":\\\"#101014\\\",\\\"peekViewResult.selectionForeground\\\":\\\"#a9b1d6\\\",\\\"peekViewResult.selectionBackground\\\":\\\"#3d59a133\\\",\\\"peekViewResult.lineForeground\\\":\\\"#a9b1d6\\\",\\\"peekViewResult.fileForeground\\\":\\\"#787c99\\\",\\\"peekViewResult.matchHighlightBackground\\\":\\\"#3d59a166\\\",\\\"diffEditor.insertedTextBackground\\\":\\\"#41a6b520\\\",\\\"diffEditor.removedTextBackground\\\":\\\"#db4b4b22\\\",\\\"diffEditor.insertedLineBackground\\\":\\\"#41a6b520\\\",\\\"diffEditor.removedLineBackground\\\":\\\"#db4b4b22\\\",\\\"diffEditorGutter.insertedLineBackground\\\":\\\"#41a6b525\\\",\\\"diffEditorGutter.removedLineBackground\\\":\\\"#db4b4b22\\\",\\\"diffEditorOverview.insertedForeground\\\":\\\"#41a6b525\\\",\\\"diffEditorOverview.removedForeground\\\":\\\"#db4b4b22\\\",\\\"diffEditor.diagonalFill\\\":\\\"#292e42\\\",\\\"diffEditor.unchangedCodeBackground\\\":\\\"#282a3b66\\\",\\\"multiDiffEditor.headerBackground\\\":\\\"#1a1b26\\\",\\\"multiDiffEditor.border\\\":\\\"#1a1b26\\\",\\\"breadcrumb.background\\\":\\\"#16161e\\\",\\\"breadcrumbPicker.background\\\":\\\"#16161e\\\",\\\"breadcrumb.foreground\\\":\\\"#515670\\\",\\\"breadcrumb.focusForeground\\\":\\\"#a9b1d6\\\",\\\"breadcrumb.activeSelectionForeground\\\":\\\"#a9b1d6\\\",\\\"tab.activeBackground\\\":\\\"#16161e\\\",\\\"tab.inactiveBackground\\\":\\\"#16161e\\\",\\\"tab.activeForeground\\\":\\\"#a9b1d6\\\",\\\"tab.hoverForeground\\\":\\\"#a9b1d6\\\",\\\"tab.activeBorder\\\":\\\"#3d59a1\\\",\\\"tab.inactiveForeground\\\":\\\"#787c99\\\",\\\"tab.border\\\":\\\"#101014\\\",\\\"tab.unfocusedActiveForeground\\\":\\\"#a9b1d6\\\",\\\"tab.unfocusedInactiveForeground\\\":\\\"#787c99\\\",\\\"tab.unfocusedHoverForeground\\\":\\\"#a9b1d6\\\",\\\"tab.activeModifiedBorder\\\":\\\"#1a1b26\\\",\\\"tab.inactiveModifiedBorder\\\":\\\"#1f202e\\\",\\\"tab.unfocusedActiveBorder\\\":\\\"#1f202e\\\",\\\"tab.lastPinnedBorder\\\":\\\"#222333\\\",\\\"panel.background\\\":\\\"#16161e\\\",\\\"panel.border\\\":\\\"#101014\\\",\\\"panelTitle.activeForeground\\\":\\\"#787c99\\\",\\\"panelTitle.inactiveForeground\\\":\\\"#42465d\\\",\\\"panelTitle.activeBorder\\\":\\\"#16161e\\\",\\\"panelInput.border\\\":\\\"#16161e\\\",\\\"statusBar.foreground\\\":\\\"#787c99\\\",\\\"statusBar.background\\\":\\\"#16161e\\\",\\\"statusBar.border\\\":\\\"#101014\\\",\\\"statusBar.noFolderBackground\\\":\\\"#16161e\\\",\\\"statusBar.debuggingBackground\\\":\\\"#16161e\\\",\\\"statusBar.debuggingForeground\\\":\\\"#787c99\\\",\\\"statusBarItem.activeBackground\\\":\\\"#101014\\\",\\\"statusBarItem.hoverBackground\\\":\\\"#20222c\\\",\\\"statusBarItem.prominentBackground\\\":\\\"#101014\\\",\\\"statusBarItem.prominentHoverBackground\\\":\\\"#20222c\\\",\\\"titleBar.activeForeground\\\":\\\"#787c99\\\",\\\"titleBar.inactiveForeground\\\":\\\"#787c99\\\",\\\"titleBar.activeBackground\\\":\\\"#16161e\\\",\\\"titleBar.inactiveBackground\\\":\\\"#16161e\\\",\\\"titleBar.border\\\":\\\"#101014\\\",\\\"walkThrough.embeddedEditorBackground\\\":\\\"#16161e\\\",\\\"textLink.foreground\\\":\\\"#6183bb\\\",\\\"textLink.activeForeground\\\":\\\"#7dcfff\\\",\\\"textPreformat.foreground\\\":\\\"#9699a8\\\",\\\"textBlockQuote.background\\\":\\\"#16161e\\\",\\\"textCodeBlock.background\\\":\\\"#16161e\\\",\\\"textSeparator.foreground\\\":\\\"#363b54\\\",\\\"debugExceptionWidget.border\\\":\\\"#963c47\\\",\\\"debugExceptionWidget.background\\\":\\\"#101014\\\",\\\"debugToolBar.background\\\":\\\"#101014\\\",\\\"debugConsole.infoForeground\\\":\\\"#787c99\\\",\\\"debugConsole.errorForeground\\\":\\\"#bb616b\\\",\\\"debugConsole.sourceForeground\\\":\\\"#787c99\\\",\\\"debugConsole.warningForeground\\\":\\\"#c49a5a\\\",\\\"debugConsoleInputIcon.foreground\\\":\\\"#73daca\\\",\\\"editor.stackFrameHighlightBackground\\\":\\\"#e2bd3a20\\\",\\\"editor.focusedStackFrameHighlightBackground\\\":\\\"#73daca20\\\",\\\"debugView.stateLabelForeground\\\":\\\"#787c99\\\",\\\"debugView.stateLabelBackground\\\":\\\"#14141b\\\",\\\"debugView.valueChangedHighlight\\\":\\\"#3d59a1aa\\\",\\\"debugTokenExpression.name\\\":\\\"#7dcfff\\\",\\\"debugTokenExpression.value\\\":\\\"#9aa5ce\\\",\\\"debugTokenExpression.string\\\":\\\"#9ece6a\\\",\\\"debugTokenExpression.boolean\\\":\\\"#ff9e64\\\",\\\"debugTokenExpression.number\\\":\\\"#ff9e64\\\",\\\"debugTokenExpression.error\\\":\\\"#bb616b\\\",\\\"debugIcon.breakpointForeground\\\":\\\"#db4b4b\\\",\\\"debugIcon.breakpointDisabledForeground\\\":\\\"#414761\\\",\\\"debugIcon.breakpointUnverifiedForeground\\\":\\\"#c24242\\\",\\\"terminal.background\\\":\\\"#16161e\\\",\\\"terminal.foreground\\\":\\\"#787c99\\\",\\\"terminal.selectionBackground\\\":\\\"#515c7e4d\\\",\\\"terminal.ansiBlack\\\":\\\"#363b54\\\",\\\"terminal.ansiRed\\\":\\\"#f7768e\\\",\\\"terminal.ansiGreen\\\":\\\"#73daca\\\",\\\"terminal.ansiYellow\\\":\\\"#e0af68\\\",\\\"terminal.ansiBlue\\\":\\\"#7aa2f7\\\",\\\"terminal.ansiMagenta\\\":\\\"#bb9af7\\\",\\\"terminal.ansiCyan\\\":\\\"#7dcfff\\\",\\\"terminal.ansiWhite\\\":\\\"#787c99\\\",\\\"terminal.ansiBrightBlack\\\":\\\"#363b54\\\",\\\"terminal.ansiBrightRed\\\":\\\"#f7768e\\\",\\\"terminal.ansiBrightGreen\\\":\\\"#41a6b5\\\",\\\"terminal.ansiBrightYellow\\\":\\\"#e0af68\\\",\\\"terminal.ansiBrightBlue\\\":\\\"#7aa2f7\\\",\\\"terminal.ansiBrightMagenta\\\":\\\"#bb9af7\\\",\\\"terminal.ansiBrightCyan\\\":\\\"#7dcfff\\\",\\\"terminal.ansiBrightWhite\\\":\\\"#acb0d0\\\",\\\"gitDecoration.modifiedResourceForeground\\\":\\\"#6183bb\\\",\\\"gitDecoration.ignoredResourceForeground\\\":\\\"#515670\\\",\\\"gitDecoration.deletedResourceForeground\\\":\\\"#914c54\\\",\\\"gitDecoration.renamedResourceForeground\\\":\\\"#449dab\\\",\\\"gitDecoration.addedResourceForeground\\\":\\\"#449dab\\\",\\\"gitDecoration.untrackedResourceForeground\\\":\\\"#449dab\\\",\\\"gitDecoration.conflictingResourceForeground\\\":\\\"#e0af68cc\\\",\\\"gitDecoration.stageDeletedResourceForeground\\\":\\\"#914c54\\\",\\\"gitDecoration.stageModifiedResourceForeground\\\":\\\"#6183bb\\\",\\\"notebook.editorBackground\\\":\\\"#1a1b26\\\",\\\"notebook.cellEditorBackground\\\":\\\"#16161e\\\",\\\"notebook.cellBorderColor\\\":\\\"#101014\\\",\\\"notebook.focusedCellBorder\\\":\\\"#29355a\\\",\\\"notebook.cellStatusBarItemHoverBackground\\\":\\\"#1c1d29\\\",\\\"charts.red\\\":\\\"#f7768e\\\",\\\"charts.blue\\\":\\\"#7aa2f7\\\",\\\"charts.yellow\\\":\\\"#e0af68\\\",\\\"charts.orange\\\":\\\"#ff9e64\\\",\\\"charts.green\\\":\\\"#41a6b5\\\",\\\"charts.purple\\\":\\\"#9d7cd8\\\",\\\"charts.foreground\\\":\\\"#9aa5ce\\\",\\\"charts.lines\\\":\\\"#16161e\\\",\\\"merge.currentHeaderBackground\\\":\\\"#41a6b525\\\",\\\"merge.currentContentBackground\\\":\\\"#007a7544\\\",\\\"merge.incomingHeaderBackground\\\":\\\"#3d59a1aa\\\",\\\"merge.incomingContentBackground\\\":\\\"#3d59a144\\\",\\\"mergeEditor.change.background\\\":\\\"#41a6b525\\\",\\\"mergeEditor.change.word.background\\\":\\\"#41a6b540\\\",\\\"mergeEditor.conflict.unhandledUnfocused.border\\\":\\\"#e0af6888\\\",\\\"mergeEditor.conflict.unhandledFocused.border\\\":\\\"#e0af68b0\\\",\\\"mergeEditor.conflict.handledUnfocused.border\\\":\\\"#41a6b525\\\",\\\"mergeEditor.conflict.handledFocused.border\\\":\\\"#41a6b565\\\",\\\"mergeEditor.conflict.handled.minimapOverViewRuler\\\":\\\"#449dab\\\",\\\"mergeEditor.conflict.unhandled.minimapOverViewRuler\\\":\\\"#e0af68\\\",\\\"gitlens.trailingLineForegroundColor\\\":\\\"#646e9c\\\",\\\"gitlens.gutterUncommittedForegroundColor\\\":\\\"#7aa2f7\\\",\\\"gitlens.gutterForegroundColor\\\":\\\"#787c99\\\",\\\"gitlens.gutterBackgroundColor\\\":\\\"#16161e\\\",\\\"notificationCenterHeader.background\\\":\\\"#101014\\\",\\\"notifications.background\\\":\\\"#101014\\\",\\\"notificationLink.foreground\\\":\\\"#6183bb\\\",\\\"notificationsErrorIcon.foreground\\\":\\\"#bb616b\\\",\\\"notificationsWarningIcon.foreground\\\":\\\"#bba461\\\",\\\"notificationsInfoIcon.foreground\\\":\\\"#0da0ba\\\",\\\"menubar.selectionForeground\\\":\\\"#a9b1d6\\\",\\\"menubar.selectionBackground\\\":\\\"#1e202e\\\",\\\"menubar.selectionBorder\\\":\\\"#1b1e2e\\\",\\\"menu.foreground\\\":\\\"#787c99\\\",\\\"menu.background\\\":\\\"#16161e\\\",\\\"menu.selectionForeground\\\":\\\"#a9b1d6\\\",\\\"menu.selectionBackground\\\":\\\"#1e202e\\\",\\\"menu.separatorBackground\\\":\\\"#101014\\\",\\\"menu.border\\\":\\\"#101014\\\"},\\\"watch\\\":false}\"},\"nps/lastSessionDate\":{\"version\":1,\"value\":\"Sun Jan 07 2024\"},\"nps/sessionCount\":{\"version\":1,\"value\":\"9\"},\"cpp.1.lastSessionDate\":{\"version\":1,\"value\":\"Wed Aug 28 2024\"},\"cpp.1.sessionCount\":{\"version\":1,\"value\":\"203\"},\"java.2.lastSessionDate\":{\"version\":1,\"value\":\"Wed Aug 28 2024\"},\"java.2.sessionCount\":{\"version\":1,\"value\":\"197\"},\"javascript.1.lastSessionDate\":{\"version\":1,\"value\":\"Sat Jan 20 2024\"},\"javascript.1.sessionCount\":{\"version\":1,\"value\":\"20\"},\"typescript.1.lastSessionDate\":{\"version\":1,\"value\":\"Fri Jun 07 2024\"},\"typescript.1.sessionCount\":{\"version\":1,\"value\":\"134\"},\"csharp.1.lastSessionDate\":{\"version\":1,\"value\":\"Wed Aug 28 2024\"},\"csharp.1.sessionCount\":{\"version\":1,\"value\":\"203\"},\"~remote.forwardedPortsContainer.hidden\":{\"version\":1,\"value\":\"[{\\\"id\\\":\\\"~remote.forwardedPorts\\\",\\\"isHidden\\\":false}]\"},\"workbench.telemetryOptOutShown\":{\"version\":1,\"value\":\"true\"},\"memento/gettingStartedService\":{\"version\":1,\"value\":\"{\\\"pickColorTheme\\\":{\\\"done\\\":true},\\\"pickColorThemeWeb\\\":{\\\"done\\\":true},\\\"settingsSync\\\":{\\\"done\\\":true},\\\"settingsSyncWeb\\\":{\\\"done\\\":true},\\\"GitHub.copilot#copilotWelcome#copilot.signin\\\":{\\\"done\\\":true},\\\"extensionsWeb\\\":{\\\"done\\\":true},\\\"findLanguageExtensions\\\":{\\\"done\\\":true},\\\"settings\\\":{\\\"done\\\":true},\\\"commandPaletteTask\\\":{\\\"done\\\":true},\\\"pickAFolderTask-Mac\\\":{\\\"done\\\":true},\\\"pickAFolderTask-Other\\\":{\\\"done\\\":true},\\\"quickOpen\\\":{\\\"done\\\":true},\\\"videoTutorial\\\":{\\\"done\\\":true},\\\"installGit\\\":{\\\"done\\\":true},\\\"terminal\\\":{\\\"done\\\":true},\\\"commandPaletteTaskWeb\\\":{\\\"done\\\":true},\\\"quickOpenWeb\\\":{\\\"done\\\":true},\\\"eamodio.gitlens#welcome#more\\\":{\\\"done\\\":true},\\\"GitHub.copilot#copilotWelcome#copilot.realfiles.quickopen\\\":{\\\"done\\\":true},\\\"vscjava.vscode-java-pack#javaWelcome#java.showProjectExplorer.inactive\\\":{\\\"done\\\":true},\\\"GitHub.copilot#copilotWelcome#copilot.iterate\\\":{\\\"done\\\":true},\\\"ms-vscode.cpptools#cppWelcome#create.cpp.file\\\":{\\\"done\\\":true},\\\"ms-vscode-remote.remote-wsl#wslWalkthrough#create.project\\\":{\\\"done\\\":true},\\\"shortcuts\\\":{\\\"done\\\":true},\\\"GitHub.copilot#copilotWelcome#copilot.realfiles.openrecent\\\":{\\\"done\\\":true},\\\"scm\\\":{\\\"done\\\":true},\\\"eamodio.gitlens#welcome#get-started\\\":{\\\"done\\\":true},\\\"eamodio.gitlens#welcome#visualize\\\":{\\\"done\\\":true},\\\"menuBarWeb\\\":{\\\"done\\\":true}}\"},\"workbench.statusbar.hidden\":{\"version\":1,\"value\":\"[\\\"status.workspaceTrust.1703394300744\\\",\\\"status.workspaceTrust.7f4b45e494e10d79b5df466acc439b61\\\",\\\"status.workspaceTrust.1703478164893\\\",\\\"status.workspaceTrust.eccd3662338556ed2ee7ecfe4846b99f\\\",\\\"status.workspaceTrust.1703487384034\\\",\\\"status.workspaceTrust.d8a0e69ae17561313901cb7b8494d9db\\\",\\\"status.workspaceTrust.8ec732a868cade5b5e9f6b7733087094\\\",\\\"status.workspaceTrust.1703610910795\\\",\\\"status.workspaceTrust.1703610932117\\\",\\\"status.workspaceTrust.1703653283629\\\",\\\"status.workspaceTrust.1703653443005\\\",\\\"status.workspaceTrust.31a12fc369f67c46e25aae7990d7956d\\\",\\\"status.workspaceTrust.4fa1ca577916f7fed8c8af7bd5ddad99\\\",\\\"status.workspaceTrust.1704379122590\\\",\\\"status.workspaceTrust.1704437172720\\\",\\\"status.workspaceTrust.1704529383690\\\",\\\"status.workspaceTrust.1704691156651\\\",\\\"status.workspaceTrust.45812a4c67802e5eacc4be8e7a89b4e6\\\",\\\"status.workspaceTrust.1704863218356\\\",\\\"status.workspaceTrust.1705062899602\\\",\\\"status.workspaceTrust.f487d9d9d774258872c82e81c5e2636f\\\",\\\"status.workspaceTrust.309b4b921c010ad464e6b90df57a29fd\\\",\\\"status.workspaceTrust.b0a2fa0757317581d000dbbb951b9e3f\\\",\\\"status.workspaceTrust.67fcc0d5dc1214ddf850e914c956a6f2\\\",\\\"status.workspaceTrust.b2447517279aeb218549e97042be01c5\\\",\\\"status.workspaceTrust.1705725203653\\\",\\\"status.workspaceTrust.44b58b71a673a842e75e214da71226f0\\\",\\\"status.workspaceTrust.abdba8473caf5349950d35a79fe7b8f0\\\",\\\"status.workspaceTrust.a51724d2be90f67b20bb957c2718d471\\\",\\\"status.workspaceTrust.13ea5e25fba9f63090ca08d53e4c9642\\\",\\\"status.workspaceTrust.079a0e0b24ba9d65ac4d17d2f21ebb23\\\",\\\"status.workspaceTrust.6821c5e5fda7c1a225ec1789a03a43a8\\\",\\\"status.workspaceTrust.eb39b82bd0179d8d4805c0c2a9b92ed5\\\",\\\"status.workspaceTrust.1706161511072\\\",\\\"status.workspaceTrust.1706161560328\\\",\\\"status.workspaceTrust.1706164092359\\\",\\\"status.workspaceTrust.1706167064750\\\",\\\"status.workspaceTrust.1706167092999\\\",\\\"status.workspaceTrust.1706177456098\\\",\\\"status.workspaceTrust.1706177573919\\\",\\\"status.workspaceTrust.40274fb490acf1ea534219a72e51e1af\\\",\\\"status.workspaceTrust.1706247843017\\\",\\\"status.workspaceTrust.1706252462887\\\",\\\"status.workspaceTrust.1706252475430\\\",\\\"status.workspaceTrust.1706253179662\\\",\\\"status.workspaceTrust.1706325971482\\\",\\\"status.workspaceTrust.1706327077290\\\",\\\"status.workspaceTrust.f6f8e7f7cdcde3dbe0b9352cb47efb42\\\",\\\"status.workspaceTrust.9ba9bf7b0e998e3c7a117d76749d24fc\\\",\\\"status.workspaceTrust.727250491bdc8ddf69c0b49c6e6e4632\\\",\\\"status.workspaceTrust.4aa56f629b05d80fda592085914a45fd\\\",\\\"status.workspaceTrust.a25b4a51e408d8b325d64fd05e0315a4\\\",\\\"status.workspaceTrust.bd4e2022724293e468dd55c06be73d19\\\",\\\"status.workspaceTrust.ff67ff13fb34010281272827b2427fec\\\",\\\"status.workspaceTrust.1706755665019\\\",\\\"status.workspaceTrust.1706762101420\\\",\\\"status.workspaceTrust.ee939e3db3742d8a5a733f4ecca9ccb9\\\",\\\"status.workspaceTrust.1707373614114\\\",\\\"status.workspaceTrust.357fc61c81c4bc2cdf05270ec83ea81f\\\",\\\"status.workspaceTrust.1707486870912\\\",\\\"status.workspaceTrust.1707487246058\\\",\\\"status.workspaceTrust.1707491738064\\\",\\\"status.workspaceTrust.1707491859751\\\",\\\"status.workspaceTrust.1707492194370\\\",\\\"status.workspaceTrust.1707530079990\\\",\\\"status.workspaceTrust.1707565044925\\\",\\\"status.workspaceTrust.1707616614580\\\",\\\"status.workspaceTrust.1707618404024\\\",\\\"status.workspaceTrust.1707804804261\\\",\\\"status.workspaceTrust.1707918535653\\\",\\\"status.workspaceTrust.1708084165378\\\",\\\"status.workspaceTrust.1708085353819\\\",\\\"status.workspaceTrust.8704474112e52e42fbe5b2d54e67fa52\\\",\\\"status.workspaceTrust.7b87a608202b82d81ed7514afefbca05\\\",\\\"status.workspaceTrust.c710802c90e050cf2e0f26a27569984b\\\",\\\"status.workspaceTrust.9b5a34d8ee7cc49ce6522135e55f6de1\\\",\\\"status.workspaceTrust.1708158668354\\\",\\\"status.workspaceTrust.1708160890892\\\",\\\"status.workspaceTrust.1708162158111\\\",\\\"status.workspaceTrust.1708166541929\\\",\\\"status.workspaceTrust.1708166557102\\\",\\\"status.workspaceTrust.1708319184299\\\",\\\"status.workspaceTrust.1708338380197\\\",\\\"status.workspaceTrust.7701df81cd5fe9616f8bcceb830e3c5d\\\"]\"},\"themeUpdatedNotificationShown\":{\"version\":1,\"value\":\"true\"},\"workbench.welcomePage.hiddenCategories\":{\"version\":1,\"value\":\"[\\\"Setup\\\",\\\"Beginner\\\",\\\"SetupWeb\\\"]\"},\"workbench.view.extensions.state.hidden\":{\"version\":1,\"value\":\"[{\\\"id\\\":\\\"workbench.views.extensions.installed\\\",\\\"isHidden\\\":false},{\\\"id\\\":\\\"workbench.views.extensions.searchOutdated\\\",\\\"isHidden\\\":false},{\\\"id\\\":\\\"workbench.views.extensions.workspaceRecommendations\\\",\\\"isHidden\\\":false},{\\\"id\\\":\\\"workbench.views.extensions.popular\\\",\\\"isHidden\\\":false},{\\\"id\\\":\\\"workbench.views.extensions.searchRecentlyUpdated\\\",\\\"isHidden\\\":false},{\\\"id\\\":\\\"workbench.views.extensions.otherRecommendations\\\",\\\"isHidden\\\":false},{\\\"id\\\":\\\"extensions.recommendedList\\\",\\\"isHidden\\\":false},{\\\"id\\\":\\\"workbench.views.extensions.enabled\\\",\\\"isHidden\\\":true},{\\\"id\\\":\\\"workbench.views.extensions.disabled\\\",\\\"isHidden\\\":true},{\\\"id\\\":\\\"workbench.views.extensions.marketplace\\\",\\\"isHidden\\\":false},{\\\"id\\\":\\\"workbench.views.extensions.searchInstalled\\\",\\\"isHidden\\\":false},{\\\"id\\\":\\\"workbench.views.extensions.searchEnabled\\\",\\\"isHidden\\\":false},{\\\"id\\\":\\\"workbench.views.extensions.searchDisabled\\\",\\\"isHidden\\\":false},{\\\"id\\\":\\\"workbench.views.extensions.searchBuiltin\\\",\\\"isHidden\\\":false},{\\\"id\\\":\\\"workbench.views.extensions.searchWorkspaceUnsupported\\\",\\\"isHidden\\\":false},{\\\"id\\\":\\\"workbench.views.extensions.builtinFeatureExtensions\\\",\\\"isHidden\\\":false},{\\\"id\\\":\\\"workbench.views.extensions.builtinThemeExtensions\\\",\\\"isHidden\\\":false},{\\\"id\\\":\\\"workbench.views.extensions.builtinProgrammingLanguageExtensions\\\",\\\"isHidden\\\":false},{\\\"id\\\":\\\"workbench.views.extensions.untrustedUnsupportedExtensions\\\",\\\"isHidden\\\":false},{\\\"id\\\":\\\"workbench.views.extensions.untrustedPartiallySupportedExtensions\\\",\\\"isHidden\\\":false},{\\\"id\\\":\\\"workbench.views.extensions.virtualUnsupportedExtensions\\\",\\\"isHidden\\\":false},{\\\"id\\\":\\\"workbench.views.extensions.virtualPartiallySupportedExtensions\\\",\\\"isHidden\\\":false},{\\\"id\\\":\\\"workbench.views.extensions.deprecatedExtensions\\\",\\\"isHidden\\\":false}]\"},\"workbench.panel.alignment\":{\"version\":1,\"value\":\"center\"},\"memento/workbench.editor.keybindings\":{\"version\":1,\"value\":\"{\\\"searchHistory\\\":[\\\"@command:editor.action.fontZoomIn\\\",\\\"@ext:vscodevim.vim\\\",\\\"\\\\\\\"ctrl+b ctrl+p\\\\\\\"\\\",\\\"ter\\\",\\\"terminla\\\",\\\"termin\\\",\\\"terminal\\\",\\\"terminal \\\",\\\"terminal vim\\\",\\\"terminal vi\\\",\\\"lead\\\",\\\"leader\\\",\\\"@source:user\\\",\\\"c\\\",\\\"@source:extension\\\",\\\"@source:extensionvim\\\",\\\"\\\\\\\"c\\\\\\\"\\\",\\\"\\\\\\\"c ctrl\\\\\\\"\\\",\\\"\\\\\\\"backspace backspace\\\\\\\"\\\",\\\"\\\\\\\"ctrl+c\\\\\\\"\\\",\\\"\\\\\\\"ctrl+f4\\\\\\\"\\\",\\\"\\\\\\\"ctrl+enter\\\\\\\"\\\",\\\"@command:editor.emmet.action.balanceOut\\\",\\\"\\\\\\\"alt+o\\\\\\\"\\\",\\\"\\\\\\\"ctrl+p\\\\\\\"\\\",\\\"\\\\\\\"ctrl+shift+i\\\\\\\"\\\",\\\"copilot\\\",\\\"vim\\\",\\\"wh\\\",\\\"vi\\\",\\\"vim \\\",\\\"vim wh\\\",\\\"vim which\\\",\\\"whic\\\",\\\"which\\\",\\\"\\\\\\\"ctrl\\\\\\\"\\\",\\\"\\\\\\\"b\\\\\\\"\\\",\\\"\\\\\\\"b backspace\\\\\\\"\\\",\\\"\\\\\\\"backspace\\\\\\\"\\\",\\\"\\\\\\\"ctrl+b\\\\\\\"\\\"]}\"},\"workbench.panel.chatSidebar.hidden\":{\"version\":1,\"value\":\"[{\\\"id\\\":\\\"workbench.panel.chat.view.copilot\\\",\\\"isHidden\\\":false}]\"},\"workbench.welcomePage.walkthroughMetadata\":{\"version\":1,\"value\":\"[[\\\"eamodio.gitlens#welcome\\\",{\\\"firstSeen\\\":1717863999707,\\\"stepIDs\\\":[\\\"get-started\\\",\\\"core-features\\\",\\\"pro-features\\\",\\\"pro-trial\\\",\\\"pro-upgrade\\\",\\\"pro-reactivate\\\",\\\"pro-paid\\\",\\\"visualize\\\",\\\"launchpad\\\",\\\"code-collab\\\",\\\"integrations\\\",\\\"more\\\"],\\\"manaullyOpened\\\":false}],[\\\"GitHub.copilot#copilotWelcome\\\",{\\\"firstSeen\\\":1717863999707,\\\"stepIDs\\\":[\\\"GitHub.copilot#copilotWelcome#copilot.signin\\\",\\\"GitHub.copilot#copilotWelcome#copilot.firstsuggest\\\",\\\"GitHub.copilot#copilotWelcome#copilot.chatWin\\\",\\\"GitHub.copilot#copilotWelcome#copilot.chatNonWin\\\",\\\"GitHub.copilot#copilotWelcome#copilot.realfiles.openrecent\\\",\\\"GitHub.copilot#copilotWelcome#copilot.realfiles.quickopen\\\",\\\"GitHub.copilot#copilotWelcome#copilot.iterate\\\",\\\"GitHub.copilot#copilotWelcome#copilot.creativity\\\"],\\\"manaullyOpened\\\":true}],[\\\"ms-vscode-remote.remote-wsl#wslWalkthrough\\\",{\\\"firstSeen\\\":1717863999707,\\\"stepIDs\\\":[\\\"explore.commands\\\",\\\"open.wslwindow\\\",\\\"create.project\\\",\\\"open.project\\\",\\\"linux.environment\\\",\\\"install.tools\\\",\\\"run.debug\\\",\\\"come.back\\\"],\\\"manaullyOpened\\\":false}],[\\\"ms-vscode.cpptools#cppWelcome\\\",{\\\"firstSeen\\\":1717863999707,\\\"stepIDs\\\":[\\\"awaiting.activation.mac\\\",\\\"awaiting.activation.linux\\\",\\\"awaiting.activation.windows\\\",\\\"awaiting.activation.windows10\\\",\\\"awaiting.activation.windows11\\\",\\\"no.compilers.found.mac\\\",\\\"no.compilers.found.linux\\\",\\\"no.compilers.found.windows\\\",\\\"no.compilers.found.windows10\\\",\\\"no.compilers.found.windows11\\\",\\\"verify.compiler.mac\\\",\\\"verify.compiler.linux\\\",\\\"verify.compiler.windows\\\",\\\"verify.compiler.windows10\\\",\\\"verify.compiler.windows11\\\",\\\"create.cpp.file\\\",\\\"relaunch.developer.command.prompt.windows\\\",\\\"run.project.mac\\\",\\\"run.project.linux\\\",\\\"run.project.windows\\\",\\\"customize.debugging.linux\\\",\\\"customize.debugging.windows\\\",\\\"customize.debugging.mac\\\"],\\\"manaullyOpened\\\":false}],[\\\"vscjava.vscode-java-pack#javaWelcome\\\",{\\\"firstSeen\\\":1717863999707,\\\"stepIDs\\\":[\\\"vscjava.vscode-java-pack#javaWelcome#java.runtime\\\",\\\"vscjava.vscode-java-pack#javaWelcome#java.showProjectExplorer\\\",\\\"vscjava.vscode-java-pack#javaWelcome#java.showProjectExplorer.inactive\\\",\\\"vscjava.vscode-java-pack#javaWelcome#java.debugAndTest\\\",\\\"vscjava.vscode-java-pack#javaWelcome#java.extensions\\\",\\\"vscjava.vscode-java-pack#javaWelcome#java.more\\\",\\\"vscjava.vscode-java-pack#javaWelcome#java.moreForMac\\\"],\\\"manaullyOpened\\\":true}],[\\\"ms-python.python#pythonWelcome\\\",{\\\"firstSeen\\\":1720326503469,\\\"stepIDs\\\":[\\\"ms-python.python#pythonWelcome#python.createPythonFolder\\\",\\\"ms-python.python#pythonWelcome#python.createPythonFile\\\",\\\"ms-python.python#pythonWelcome#python.installPythonWin8\\\",\\\"ms-python.python#pythonWelcome#python.installPythonMac\\\",\\\"ms-python.python#pythonWelcome#python.installPythonLinux\\\",\\\"ms-python.python#pythonWelcome#python.createEnvironment\\\",\\\"ms-python.python#pythonWelcome#python.runAndDebug\\\",\\\"ms-python.python#pythonWelcome#python.learnMoreWithDS\\\"],\\\"manaullyOpened\\\":true}],[\\\"ms-python.python#pythonDataScienceWelcome\\\",{\\\"firstSeen\\\":1720326503469,\\\"stepIDs\\\":[\\\"python.installJupyterExt\\\",\\\"python.createNewNotebook\\\",\\\"python.openInteractiveWindow\\\",\\\"python.dataScienceLearnMore\\\"],\\\"manaullyOpened\\\":false}],[\\\"ms-azuretools.vscode-docker#dockerStart\\\",{\\\"firstSeen\\\":1723351230837,\\\"stepIDs\\\":[\\\"openFolder\\\",\\\"openFolderMac\\\",\\\"scaffold\\\",\\\"buildImage\\\",\\\"runContainer\\\",\\\"dockerExplorer\\\",\\\"pushImage\\\",\\\"azDeploy\\\",\\\"learn\\\"],\\\"manaullyOpened\\\":false}]]\"},\"workbench.view.remote.state.hidden\":{\"version\":1,\"value\":\"[{\\\"id\\\":\\\"github.codespaces.explorer\\\",\\\"isHidden\\\":false},{\\\"id\\\":\\\"github.codespaces.warnExplorer\\\",\\\"isHidden\\\":false},{\\\"id\\\":\\\"github.codespaces.performanceExplorer\\\",\\\"isHidden\\\":false},{\\\"id\\\":\\\"targetsWsl\\\",\\\"isHidden\\\":false},{\\\"id\\\":\\\"~remote.helpPanel\\\",\\\"isHidden\\\":false},{\\\"id\\\":\\\"targetsContainers\\\",\\\"isHidden\\\":false},{\\\"id\\\":\\\"detailsContainers\\\",\\\"isHidden\\\":false},{\\\"id\\\":\\\"devVolumes\\\",\\\"isHidden\\\":false}]\"},\"github-KashifKhn\":{\"version\":1,\"value\":\"[{\\\"id\\\":\\\"github.copilot\\\",\\\"name\\\":\\\"GitHub Copilot\\\",\\\"allowed\\\":true},{\\\"id\\\":\\\"vscode.github\\\",\\\"name\\\":\\\"GitHub\\\",\\\"allowed\\\":true},{\\\"id\\\":\\\"github.vscode-github-actions\\\",\\\"name\\\":\\\"GitHub Actions\\\",\\\"allowed\\\":true}]\"},\"javascript.1.editedCount\":{\"version\":1,\"value\":\"10\"},\"javascript.1.editedDate\":{\"version\":1,\"value\":\"Fri Jan 19 2024\"},\"workbench.view.extension.gitlens.state.hidden\":{\"version\":1,\"value\":\"[{\\\"id\\\":\\\"gitlens.views.home\\\",\\\"isHidden\\\":false},{\\\"id\\\":\\\"gitlens.views.drafts\\\",\\\"isHidden\\\":false},{\\\"id\\\":\\\"gitlens.views.workspaces\\\",\\\"isHidden\\\":false},{\\\"id\\\":\\\"gitlens.views.account\\\",\\\"isHidden\\\":false},{\\\"id\\\":\\\"gitlens.views.launchpad\\\",\\\"isHidden\\\":false}]\"},\"workbench.view.extension.gitlensInspect.state.hidden\":{\"version\":1,\"value\":\"[{\\\"id\\\":\\\"gitlens.views.commitDetails\\\",\\\"isHidden\\\":false},{\\\"id\\\":\\\"gitlens.views.lineHistory\\\",\\\"isHidden\\\":false},{\\\"id\\\":\\\"gitlens.views.fileHistory\\\",\\\"isHidden\\\":false},{\\\"id\\\":\\\"gitlens.views.timeline\\\",\\\"isHidden\\\":false},{\\\"id\\\":\\\"gitlens.views.searchAndCompare\\\",\\\"isHidden\\\":false},{\\\"id\\\":\\\"gitlens.views.pullRequest\\\",\\\"isHidden\\\":false}]\"},\"workbench.view.extension.dockerView.state.hidden\":{\"version\":1,\"value\":\"[{\\\"id\\\":\\\"dockerContainers\\\",\\\"isHidden\\\":false},{\\\"id\\\":\\\"dockerImages\\\",\\\"isHidden\\\":false},{\\\"id\\\":\\\"dockerRegistries\\\",\\\"isHidden\\\":false},{\\\"id\\\":\\\"dockerNetworks\\\",\\\"isHidden\\\":false},{\\\"id\\\":\\\"dockerVolumes\\\",\\\"isHidden\\\":false},{\\\"id\\\":\\\"vscode-docker.views.dockerContexts\\\",\\\"isHidden\\\":false},{\\\"id\\\":\\\"vscode-docker.views.help\\\",\\\"isHidden\\\":false}]\"},\"snippets.usageTimestamps\":{\"version\":1,\"value\":\"[[\\\"lib/snippets/generated.json/useEffect\\\",1703396407646],[\\\"snippets/javascript.code-snippets/Function Statement\\\",1705471817713],[\\\"snippets/javascript.code-snippets/Set Timeout Function\\\",1705550447235],[\\\"javascript.json/console.error\\\",1705725388856],[\\\"snippets/snippets.json/requireToConst\\\",1705918834913],[\\\"lib/snippets/generated.json/exportDefault\\\",1706247613670],[\\\"snippets.json/fa5-not-equal\\\",1706417643005],[\\\"snippets.json/@fa5-stack\\\",1706646685433],[\\\"snippets.json/fa4-assistive-listening-systems\\\",1706646710077],[\\\"snippets/snippets.json/EJS TAG Output Escaped\\\",1706651045844],[\\\"snippets/snippets.json/EJS TAG Else If Statement\\\",1706973791338],[\\\"snippets/snippets.json/EJS TAG Output Value\\\",1707372112292],[\\\"lib/snippets/generated.json/componentProps\\\",1707451798127],[\\\"snippets/snippets.json/method\\\",1707580343728],[\\\"snippets/snippets.json/EJS TAG\\\",1707623952820],[\\\"snippets/javascript.code-snippets/Log to the console\\\",1707643692100],[\\\"javascript.json/try catch\\\",1708162956706],[\\\"snippets/snippets.json/forIn\\\",1709616463545],[\\\"snippets/javascript.code-snippets/Set Interval Function\\\",1711200029503],[\\\"snippets/snippets.json/constructor\\\",1713169872300],[\\\"snippets/javascript.code-snippets/Log error to console\\\",1714201123956],[\\\"lib/snippets/generated.json/import\\\",1715061861939],[\\\"javascript.json/express\\\",1716130583603],[\\\"lib/snippets/generated.json/reactClassExportComponent\\\",1716266136829],[\\\"lib/snippets/generated.json/getDerivedStateFromProps\\\",1716619399182],[\\\"lib/snippets/generated.json/consoleLogObject\\\",1716694689504],[\\\"lib/snippets/generated.json/consoleLog\\\",1716695725015],[\\\"javascript.json/UseState\\\",1716878809441],[\\\"lib/snippets/generated.json/reactArrowFunctionComponent\\\",1717069206711],[\\\"lib/snippets/generated.json/testBlock\\\",1717679670265],[\\\"snippets/typescript.code-snippets/Set Timeout Function\\\",1717773533005],[\\\"javascript.json/express with mongoose\\\",1721710451473],[\\\"javascript.json/console.log\\\",1721923533087],[\\\"snippets/typescript.code-snippets/Property setter\\\",1723486529976],[\\\"snippets/typescript.code-snippets/For-Each Loop using =>\\\",1723566531816],[\\\"lib/snippets/generated.json/reactArrowFunctionExportComponent\\\",1724222726725],[\\\"snippets/typescript.code-snippets/Try-Catch Statement\\\",1724266816719],[\\\"typescriptreact.json/console.log\\\",1724339712329],[\\\"typescript.json/console.log\\\",1724422461735]]\"},\"ces/skipSurvey\":{\"version\":1,\"value\":\"1.85.1\"},\"typescript.1.editedCount\":{\"version\":1,\"value\":\"10\"},\"typescript.1.editedDate\":{\"version\":1,\"value\":\"Thu Jun 06 2024\"},\"workbench.view.extension.test.state.hidden\":{\"version\":1,\"value\":\"[{\\\"id\\\":\\\"workbench.view.testing\\\",\\\"isHidden\\\":false},{\\\"id\\\":\\\"workbench.view.testCoverage\\\",\\\"isHidden\\\":false}]\"},\"java.2.editedCount\":{\"version\":1,\"value\":\"10\"},\"java.2.editedDate\":{\"version\":1,\"value\":\"Thu Mar 07 2024\"},\"fileBasedRecommendations/promptedRecommendations\":{\"version\":1,\"value\":\"{\\\"c\\\":[\\\"ms-vscode.cpptools-extension-pack\\\"],\\\"powershell\\\":[\\\"ms-vscode.powershell\\\"],\\\"python\\\":[\\\"ms-python.python\\\"],\\\"plaintext\\\":[\\\"tomoki1207.pdf\\\"],\\\"yaml\\\":[\\\"github.vscode-github-actions\\\"]}\"},\"inline-chat-history\":{\"version\":1,\"value\":\"[\\\"/fix Argument expression expected., Declaration or statement expected.\\\",\\\"/tests\\\",\\\"/doc\\\",\\\"/fix Declaration or statement expected.\\\",\\\"/fix Unnecessary try/catch wrapper.\\\",\\\"/fix Syntax error on token \\\\\\\"extends\\\\\\\", Type expected after this token\\\",\\\"/fix Duplicate object key\\\"]\"},\"commandPalette.mru.cache\":{\"version\":1,\"value\":\"{\\\"usesLRU\\\":true,\\\"entries\\\":[{\\\"key\\\":\\\"workbench.action.chat.open\\\",\\\"value\\\":1},{\\\"key\\\":\\\"editor.action.formatDocument\\\",\\\"value\\\":7},{\\\"key\\\":\\\"editor.action.formatDocument.multiple\\\",\\\"value\\\":8},{\\\"key\\\":\\\"welcome.showNewFileEntries\\\",\\\"value\\\":17},{\\\"key\\\":\\\"workbench.action.activityBarLocation.hide\\\",\\\"value\\\":40},{\\\"key\\\":\\\"workbench.action.toggleMenuBar\\\",\\\"value\\\":42},{\\\"key\\\":\\\"workbench.action.toggleStatusbarVisibility\\\",\\\"value\\\":44},{\\\"key\\\":\\\"workbench.action.toggleAuxiliaryBar\\\",\\\"value\\\":45},{\\\"key\\\":\\\"copyRelativeFilePath\\\",\\\"value\\\":46},{\\\"key\\\":\\\"editor.emmet.action.balanceOut\\\",\\\"value\\\":51},{\\\"key\\\":\\\"workbench.action.openGlobalKeybindings\\\",\\\"value\\\":65},{\\\"key\\\":\\\"workbench.action.openGlobalKeybindingsFile\\\",\\\"value\\\":66},{\\\"key\\\":\\\"workbench.action.openSettingsJson\\\",\\\"value\\\":69}]}\"},\"commandPalette.mru.counter\":{\"version\":1,\"value\":\"70\"},\"workbench.view.extension.gitlensPanel.state.hidden\":{\"version\":1,\"value\":\"[{\\\"id\\\":\\\"gitlens.views.graph\\\",\\\"isHidden\\\":false},{\\\"id\\\":\\\"gitlens.views.graphDetails\\\",\\\"isHidden\\\":false}]\"},\"expandSuggestionDocs\":{\"version\":1,\"value\":\"true\"},\"workbench.view.extension.vscode-serial-monitor-tools.state.hidden\":{\"version\":1,\"value\":\"[{\\\"id\\\":\\\"vscode-serial-monitor.monitor0\\\",\\\"isHidden\\\":false},{\\\"id\\\":\\\"vscode-serial-monitor.monitor1\\\",\\\"isHidden\\\":false},{\\\"id\\\":\\\"vscode-serial-monitor.monitor2\\\",\\\"isHidden\\\":false}]\"},\"nps/isCandidate\":{\"version\":1,\"value\":\"false\"},\"nps/skipVersion\":{\"version\":1,\"value\":\"1.85.1\"},\"terminal.integrated.showTerminalConfigPrompt\":{\"version\":1,\"value\":\"false\"},\"javascript.1.isCandidate\":{\"version\":1,\"value\":\"false\"},\"javascript.1.skipVersion\":{\"version\":1,\"value\":\"1.85.1\"},\"tabs-list-width-horizontal\":{\"version\":1,\"value\":\"124\"},\"workbench.view.extension.dataworkspace.state.hidden\":{\"version\":1,\"value\":\"[{\\\"id\\\":\\\"dataworkspace.views.main\\\",\\\"isHidden\\\":false}]\"},\"workbench.view.extension.objectExplorer.state.hidden\":{\"version\":1,\"value\":\"[{\\\"id\\\":\\\"objectExplorer\\\",\\\"isHidden\\\":false},{\\\"id\\\":\\\"queryHistory\\\",\\\"isHidden\\\":false}]\"},\"workbench.view.extension.sqltoolsActivityBarContainer.state.hidden\":{\"version\":1,\"value\":\"[{\\\"id\\\":\\\"sqltoolsViewConnectionExplorer\\\",\\\"isHidden\\\":false},{\\\"id\\\":\\\"sqltoolsViewBookmarksExplorer\\\",\\\"isHidden\\\":false},{\\\"id\\\":\\\"sqltoolsViewHistoryExplorer\\\",\\\"isHidden\\\":false}]\"},\"workbench.view.extension.sqltoolsPanelContainer.state.hidden\":{\"version\":1,\"value\":\"[{\\\"id\\\":\\\"sqltoolsViewConsoleMessages\\\",\\\"isHidden\\\":false}]\"},\"workbench.view.extension.github-cweijan-mysql.state.hidden\":{\"version\":1,\"value\":\"[{\\\"id\\\":\\\"github.cweijan.mysql\\\",\\\"isHidden\\\":false}]\"},\"workbench.view.extension.github-cweijan-nosql.state.hidden\":{\"version\":1,\"value\":\"[{\\\"id\\\":\\\"github.cweijan.nosql\\\",\\\"isHidden\\\":false}]\"},\"remoteTunnelServicePromptedPreview\":{\"version\":1,\"value\":\"true\"},\"workbench.view.extension.blackbox.state.hidden\":{\"version\":1,\"value\":\"[{\\\"id\\\":\\\"blackbox-onboarding\\\",\\\"isHidden\\\":false}]\"},\"workbench.view.extension.blackbox-terminal.state.hidden\":{\"version\":1,\"value\":\"[{\\\"id\\\":\\\"terminal.search.view\\\",\\\"isHidden\\\":false}]\"},\"java.2.isCandidate\":{\"version\":1,\"value\":\"true\"},\"scm.input.lastActionId\":{\"version\":1,\"value\":\"github.copilot.git.generateCommitMessage\"},\"refactorPreview.hidden\":{\"version\":1,\"value\":\"[{\\\"id\\\":\\\"refactorPreview\\\",\\\"isHidden\\\":false}]\"},\"workbench.view.extension.references-view.state.hidden\":{\"version\":1,\"value\":\"[{\\\"id\\\":\\\"references-view.tree\\\",\\\"isHidden\\\":false},{\\\"id\\\":\\\"CppReferencesView\\\",\\\"isHidden\\\":false}]\"},\"extension.features.state\":{\"version\":1,\"value\":\"{\\\"GitHub.copilot-chat\\\":{\\\"languageModels\\\":{\\\"disabled\\\":false,\\\"accessCount\\\":857}}}\"},\"languageModelAccess.copilot-gpt-3.5-turbo\":{\"version\":1,\"value\":\"[\\\"github.copilot-chat\\\"]\"},\"languageModelStats.copilot-gpt-3.5-turbo\":{\"version\":1,\"value\":\"{\\\"extensions\\\":[{\\\"extensionId\\\":\\\"GitHub.copilot-chat\\\",\\\"requestCount\\\":19,\\\"tokenCount\\\":35286,\\\"participants\\\":[{\\\"id\\\":\\\"git-commit\\\",\\\"requestCount\\\":177,\\\"tokenCount\\\":215108},{\\\"id\\\":\\\"github.copilot.editor\\\",\\\"requestCount\\\":1,\\\"tokenCount\\\":590},{\\\"id\\\":\\\"symbol-names\\\",\\\"requestCount\\\":15,\\\"tokenCount\\\":16572}]}]}\"},\"languageModelAccess.copilot-gpt-4\":{\"version\":1,\"value\":\"[\\\"github.copilot-chat\\\"]\"},\"languageModelStats.copilot-gpt-4\":{\"version\":1,\"value\":\"{\\\"extensions\\\":[{\\\"extensionId\\\":\\\"GitHub.copilot-chat\\\",\\\"requestCount\\\":0,\\\"tokenCount\\\":0,\\\"participants\\\":[{\\\"id\\\":\\\"github.copilot.default\\\",\\\"requestCount\\\":20,\\\"tokenCount\\\":36117}]}]}\"},\"userDataProfiles.state.hidden\":{\"version\":1,\"value\":\"[{\\\"id\\\":\\\"workbench.views.profiles.export.preview\\\",\\\"isHidden\\\":false}]\"},\"workbench.view.extension.amazonq.state.hidden\":{\"version\":1,\"value\":\"[{\\\"id\\\":\\\"aws.amazonq.AmazonCommonAuth\\\",\\\"isHidden\\\":false},{\\\"id\\\":\\\"aws.AmazonQChatView\\\",\\\"isHidden\\\":false},{\\\"id\\\":\\\"aws.AmazonQNeverShowBadge\\\",\\\"isHidden\\\":false}]\"},\"workbench.view.extension.aws-codewhisperer-reference-log.state.hidden\":{\"version\":1,\"value\":\"[{\\\"id\\\":\\\"aws.codeWhisperer.referenceLog\\\",\\\"isHidden\\\":false}]\"},\"workbench.view.extension.thunder-client.state.hidden\":{\"version\":1,\"value\":\"[{\\\"id\\\":\\\"thunder-client-sidebar\\\",\\\"isHidden\\\":false}]\"},\"typescript.1.isCandidate\":{\"version\":1,\"value\":\"false\"},\"typescript.1.skipVersion\":{\"version\":1,\"value\":\"1.90.0\"},\"Comments.hidden\":{\"version\":1,\"value\":\"[{\\\"id\\\":\\\"workbench.panel.comments\\\",\\\"isHidden\\\":false}]\"},\"languageModelAccess.gpt-3.5-turbo\":{\"version\":1,\"value\":\"[\\\"github.copilot-chat\\\"]\"},\"languageModelStats.gpt-3.5-turbo\":{\"version\":1,\"value\":\"{\\\"extensions\\\":[{\\\"extensionId\\\":\\\"GitHub.copilot-chat\\\",\\\"requestCount\\\":9,\\\"tokenCount\\\":9678,\\\"participants\\\":[{\\\"id\\\":\\\"git-commit\\\",\\\"requestCount\\\":522,\\\"tokenCount\\\":707623},{\\\"id\\\":\\\"symbol-names\\\",\\\"requestCount\\\":49,\\\"tokenCount\\\":16284},{\\\"id\\\":\\\"github.copilot.editor\\\",\\\"requestCount\\\":35,\\\"tokenCount\\\":42153}]}]}\"},\"encryption.migratedToGnomeLibsecret\":{\"version\":1,\"value\":\"true\"},\"languageModelAccess.gpt-4-0125-preview\":{\"version\":1,\"value\":\"[\\\"github.copilot-chat\\\"]\"},\"languageModelStats.gpt-4-0125-preview\":{\"version\":1,\"value\":\"{\\\"extensions\\\":[{\\\"extensionId\\\":\\\"GitHub.copilot-chat\\\",\\\"requestCount\\\":0,\\\"tokenCount\\\":0,\\\"participants\\\":[{\\\"id\\\":\\\"github.copilot.workspace\\\",\\\"requestCount\\\":1,\\\"tokenCount\\\":513},{\\\"id\\\":\\\"github.copilot.default\\\",\\\"requestCount\\\":4,\\\"tokenCount\\\":3263}]}]}\"},\"languageModelAccess.gpt-4o-2024-05-13\":{\"version\":1,\"value\":\"[\\\"github.copilot-chat\\\"]\"},\"languageModelStats.gpt-4o-2024-05-13\":{\"version\":1,\"value\":\"{\\\"extensions\\\":[{\\\"extensionId\\\":\\\"GitHub.copilot-chat\\\",\\\"requestCount\\\":0,\\\"tokenCount\\\":0,\\\"participants\\\":[{\\\"id\\\":\\\"github.copilot.workspace\\\",\\\"requestCount\\\":2,\\\"tokenCount\\\":3491},{\\\"id\\\":\\\"github.copilot.editor\\\",\\\"requestCount\\\":1,\\\"tokenCount\\\":1157},{\\\"id\\\":\\\"github.copilot.default\\\",\\\"requestCount\\\":2,\\\"tokenCount\\\":2494}]}]}\"},\"workbench.view.extension.github-actions.state.hidden\":{\"version\":1,\"value\":\"[{\\\"id\\\":\\\"github-actions.current-branch\\\",\\\"isHidden\\\":false},{\\\"id\\\":\\\"github-actions.workflows\\\",\\\"isHidden\\\":false},{\\\"id\\\":\\\"github-actions.settings\\\",\\\"isHidden\\\":false},{\\\"id\\\":\\\"github-actions.empty-view\\\",\\\"isHidden\\\":false}]\"},\"workbench.view.extension.package-explorer.state.hidden\":{\"version\":1,\"value\":\"[{\\\"id\\\":\\\"workspaceEnvironments\\\",\\\"isHidden\\\":false},{\\\"id\\\":\\\"pythonEnvironments\\\",\\\"isHidden\\\":false}]\"}}}"}}